{"document_id": "d3b3de321bd61e318e94095e9f9d0f31", "importance_score": 1.244, "initial_importance": 1, "origin": "SynthetischerFall", "document_label": {"group_id": "0", "importance_score": 0, "annotation_type": "document_label", "annotations": [{"annotation_id": "0", "annotator_id": "folder_model", "annotator_type": "model", "annotation_vector": [0, 0, 0, 0, 0, 0, 1, 0, 0, 0, 0, 0, 0, 0, 0, 0, 0, 0, 0], "is_other": "", "annotation_type": "document_label"}, {"annotation_id": "4ud2hDbL", "annotator_id": "AleX", "annotator_type": "human", "annotation_vector": [0, 0, 0, 0, 0, 0, 1, 0, 0, 0, 0, 0, 0, 0, 0, 0, 0, 0, 0], "is_other": "", "annotation_type": "document_label"}]}, "document_type": {"group_id": "1", "importance_score": 0, "annotation_type": "document_type", "annotations": [{"annotation_id": "52K6svlS", "annotator_id": "AleX", "annotator_type": "human", "annotation_vector": [1, 0, 0], "is_other": "", "annotation_type": "document_type"}]}, "document_contains": {"group_id": "2", "importance_score": 0, "annotation_type": "document_contains", "annotations": [{"annotation_id": "XFSaxEJW", "annotator_id": "AleX", "annotator_type": "human", "annotation_vector": [1, 0, 0, 0, 0, 0, 0, 0, 0, 1, 1, 0, 0, 0], "is_other": "", "annotation_type": "document_contains"}, {"annotation_id": "tk5mYZZn", "annotator_id": "bbu", "annotator_type": "human", "annotation_vector": [1, 1, 1, 1, 1, 1, 1, 1, 1, 1, 1, 1, 1, 1], "is_other": "", "annotation_type": "document_contains"}]}, "pages": [{"page_number": 0, "segments": [{"segment_id": "1tdXhE3L", "annotation_groups": {"segment_boundary": {"group_id": "0", "importance_score": 0, "annotation_type": "segment_boundary", "annotations": [{"annotation_id": "VcKhUqCS", "annotator_id": "schne", "annotator_type": "human", "annotation_vector": [0.3300636373763981, 0.09069691909963155, 0.6807562520888211, 0.1490437586458228], "is_other": "", "annotation_type": "segment_boundary"}]}, "segment_label": {"group_id": "1", "importance_score": 0, "annotation_type": "segment_label", "annotations": [{"annotation_id": "rEuF6EPB", "annotator_id": "schne", "annotator_type": "human", "annotation_vector": [0, 0, 0, 0, 0, 0, 0, 0, 0, 1], "is_other": "", "annotation_type": "segment_label"}]}, "is_occluded": {"group_id": "2", "importance_score": 0, "annotation_type": "is_occluded", "annotations": [{"annotation_id": "qbE0aygL", "annotator_id": "schne", "annotator_type": "human", "annotation_vector": [0, 1], "is_other": "", "annotation_type": "is_occluded"}]}, "is_truncated": {"group_id": "3", "importance_score": 1, "annotation_type": "is_truncated", "annotations": []}, "segment_type": {"group_id": "4", "importance_score": 0, "annotation_type": "segment_type", "annotations": [{"annotation_id": "8hfWFr55", "annotator_id": "schne", "annotator_type": "human", "annotation_vector": [1, 0, 0, 0], "is_other": "", "annotation_type": "segment_type"}]}}, "child_segments": []}, {"segment_id": "CGY7B2b3", "annotation_groups": {"segment_boundary": {"group_id": "0", "importance_score": 0, "annotation_type": "segment_boundary", "annotations": [{"annotation_id": "VEsx9DeF", "annotator_id": "schne", "annotator_type": "human", "annotation_vector": [0.10772910386590771, 0.3727066435728893, 0.9305960887140113, 0.9302431103476058], "is_other": "", "annotation_type": "segment_boundary"}]}, "segment_label": {"group_id": "1", "importance_score": 0, "annotation_type": "segment_label", "annotations": [{"annotation_id": "9nHUoLQz", "annotator_id": "schne", "annotator_type": "human", "annotation_vector": [0, 0, 0, 0, 0, 0, 0, 0, 0, 0], "is_other": "is_other", "annotation_type": "segment_label"}]}, "is_occluded": {"group_id": "2", "importance_score": 0, "annotation_type": "is_occluded", "annotations": [{"annotation_id": "zHaIZhFJ", "annotator_id": "schne", "annotator_type": "human", "annotation_vector": [0, 1], "is_other": "", "annotation_type": "is_occluded"}]}, "is_truncated": {"group_id": "3", "importance_score": 1, "annotation_type": "is_truncated", "annotations": []}, "segment_type": {"group_id": "4", "importance_score": 0, "annotation_type": "segment_type", "annotations": [{"annotation_id": "MUGaPDpl", "annotator_id": "schne", "annotator_type": "human", "annotation_vector": [1, 0, 0, 0], "is_other": "", "annotation_type": "segment_type"}]}}, "child_segments": []}, {"segment_id": "W7FopgHQ", "annotation_groups": {"segment_boundary": {"group_id": "0", "importance_score": 0, "annotation_type": "segment_boundary", "annotations": [{"annotation_id": "eCLYi3ce", "annotator_id": "bbu", "annotator_type": "human", "annotation_vector": [0.3454557673145777, 0.10189953132110725, 0.6774936487333975, 0.1518029388944721], "is_other": "", "annotation_type": "segment_boundary"}]}, "segment_label": {"group_id": "1", "importance_score": 0, "annotation_type": "segment_label", "annotations": [{"annotation_id": "numpMlci", "annotator_id": "bbu", "annotator_type": "human", "annotation_vector": [1, 0, 0, 0, 0, 0, 0, 0, 0, 0], "is_other": "", "annotation_type": "segment_label"}]}, "is_occluded": {"group_id": "2", "importance_score": 0, "annotation_type": "is_occluded", "annotations": [{"annotation_id": "eW9Mc4f0", "annotator_id": "bbu", "annotator_type": "human", "annotation_vector": [0, 1], "is_other": "", "annotation_type": "is_occluded"}]}, "is_truncated": {"group_id": "3", "importance_score": 1, "annotation_type": "is_truncated", "annotations": []}, "segment_type": {"group_id": "4", "importance_score": 0, "annotation_type": "segment_type", "annotations": [{"annotation_id": "6m5Qd0kg", "annotator_id": "bbu", "annotator_type": "human", "annotation_vector": [1, 0, 0, 0], "is_other": "", "annotation_type": "segment_type"}]}}, "child_segments": []}, {"segment_id": "WK8AqsuO", "annotation_groups": {"segment_boundary": {"group_id": "0", "importance_score": 0, "annotation_type": "segment_boundary", "annotations": [{"annotation_id": "DsgjIe2r", "annotator_id": "bbu", "annotator_type": "human", "annotation_vector": [0.3500042314436026, 0.10833868068541241, 0.6661224884108352, 0.15663230091770097], "is_other": "", "annotation_type": "segment_boundary"}]}, "segment_label": {"group_id": "1", "importance_score": 0, "annotation_type": "segment_label", "annotations": [{"annotation_id": "zNcBRena", "annotator_id": "bbu", "annotator_type": "human", "annotation_vector": [0, 0, 0, 0, 0, 0, 0, 0, 0, 1], "is_other": "", "annotation_type": "segment_label"}]}, "is_occluded": {"group_id": "2", "importance_score": 0, "annotation_type": "is_occluded", "annotations": [{"annotation_id": "APU2Ed3M", "annotator_id": "bbu", "annotator_type": "human", "annotation_vector": [0, 1], "is_other": "", "annotation_type": "is_occluded"}]}, "is_truncated": {"group_id": "3", "importance_score": 1, "annotation_type": "is_truncated", "annotations": []}, "segment_type": {"group_id": "4", "importance_score": 0, "annotation_type": "segment_type", "annotations": [{"annotation_id": "m5MnYceO", "annotator_id": "bbu", "annotator_type": "human", "annotation_vector": [1, 0, 0, 0], "is_other": "", "annotation_type": "segment_type"}]}}, "child_segments": []}, {"segment_id": "WV0ibLPn", "annotation_groups": {"segment_boundary": {"group_id": "0", "importance_score": 0, "annotation_type": "segment_boundary", "annotations": [{"annotation_id": "87qjygsY", "annotator_id": "bbu", "annotator_type": "human", "annotation_vector": [0.1089356326052814, 0.38361231600945733, 0.9094653193136688, 0.9100127765414029], "is_other": "", "annotation_type": "segment_boundary"}]}, "segment_label": {"group_id": "1", "importance_score": 0, "annotation_type": "segment_label", "annotations": [{"annotation_id": "6LNQyoad", "annotator_id": "bbu", "annotator_type": "human", "annotation_vector": [0, 0, 0, 0, 0, 0, 0, 0, 0, 0], "is_other": "Auflistung", "annotation_type": "segment_label"}]}, "is_occluded": {"group_id": "2", "importance_score": 0, "annotation_type": "is_occluded", "annotations": [{"annotation_id": "V57GrVHH", "annotator_id": "bbu", "annotator_type": "human", "annotation_vector": [0, 1], "is_other": "", "annotation_type": "is_occluded"}]}, "is_truncated": {"group_id": "3", "importance_score": 1, "annotation_type": "is_truncated", "annotations": []}, "segment_type": {"group_id": "4", "importance_score": 0, "annotation_type": "segment_type", "annotations": [{"annotation_id": "GGKSTyNR", "annotator_id": "bbu", "annotator_type": "human", "annotation_vector": [1, 0, 0, 0], "is_other": "", "annotation_type": "segment_type"}]}}, "child_segments": []}]}, {"page_number": 1, "segments": [{"segment_id": "cX9GlV8L", "annotation_groups": {"segment_boundary": {"group_id": "0", "importance_score": 0, "annotation_type": "segment_boundary", "annotations": [{"annotation_id": "y5eDodLB", "annotator_id": "schne", "annotator_type": "human", "annotation_vector": [0.036673737486266456, 0.06087522336690895, 0.9237197629353364, 0.9036628809701683], "is_other": "", "annotation_type": "segment_boundary"}]}, "segment_label": {"group_id": "1", "importance_score": 0, "annotation_type": "segment_label", "annotations": [{"annotation_id": "4IVvI6Uc", "annotator_id": "schne", "annotator_type": "human", "annotation_vector": [0, 0, 0, 0, 0, 0, 0, 0, 0, 0], "is_other": "is_other", "annotation_type": "segment_label"}]}, "is_occluded": {"group_id": "2", "importance_score": 0, "annotation_type": "is_occluded", "annotations": [{"annotation_id": "1Ut7oByE", "annotator_id": "schne", "annotator_type": "human", "annotation_vector": [0, 1], "is_other": "", "annotation_type": "is_occluded"}]}, "is_truncated": {"group_id": "3", "importance_score": 1, "annotation_type": "is_truncated", "annotations": []}, "segment_type": {"group_id": "4", "importance_score": 0, "annotation_type": "segment_type", "annotations": [{"annotation_id": "851WB96r", "annotator_id": "schne", "annotator_type": "human", "annotation_vector": [1, 0, 0, 0], "is_other": "", "annotation_type": "segment_type"}]}}, "child_segments": []}, {"segment_id": "sCRKjduL", "annotation_groups": {"segment_boundary": {"group_id": "0", "importance_score": 0, "annotation_type": "segment_boundary", "annotations": [{"annotation_id": "5pVg3Ttd", "annotator_id": "bbu", "annotator_type": "human", "annotation_vector": [0.09983870434723154, 0.07549902875281835, 0.9094653193136689, 0.9158080207946396], "is_other": "", "annotation_type": "segment_boundary"}]}, "segment_label": {"group_id": "1", "importance_score": 0, "annotation_type": "segment_label", "annotations": [{"annotation_id": "jwkffal1", "annotator_id": "bbu", "annotator_type": "human", "annotation_vector": [0, 0, 0, 0, 0, 0, 0, 0, 0, 0], "is_other": "Auflistung", "annotation_type": "segment_label"}]}, "is_occluded": {"group_id": "2", "importance_score": 0, "annotation_type": "is_occluded", "annotations": [{"annotation_id": "uqhTCaBE", "annotator_id": "bbu", "annotator_type": "human", "annotation_vector": [0, 1], "is_other": "", "annotation_type": "is_occluded"}]}, "is_truncated": {"group_id": "3", "importance_score": 1, "annotation_type": "is_truncated", "annotations": []}, "segment_type": {"group_id": "4", "importance_score": 0, "annotation_type": "segment_type", "annotations": [{"annotation_id": "tviwegIr", "annotator_id": "bbu", "annotator_type": "human", "annotation_vector": [1, 0, 0, 0], "is_other": "", "annotation_type": "segment_type"}]}}, "child_segments": []}]}, {"page_number": 2, "segments": [{"segment_id": "ZZ2ZaR6l", "annotation_groups": {"segment_boundary": {"group_id": "0", "importance_score": 0, "annotation_type": "segment_boundary", "annotations": [{"annotation_id": "VoZUb3kk", "annotator_id": "schne", "annotator_type": "human", "annotation_vector": [0.07105536637964126, 0.04401945488186285, 0.9214276543424448, 0.904635338188184], "is_other": "", "annotation_type": "segment_boundary"}]}, "segment_label": {"group_id": "1", "importance_score": 0, "annotation_type": "segment_label", "annotations": [{"annotation_id": "MowU3gwO", "annotator_id": "schne", "annotator_type": "human", "annotation_vector": [0, 0, 0, 0, 0, 0, 0, 0, 0, 0], "is_other": "is_other", "annotation_type": "segment_label"}]}, "is_occluded": {"group_id": "2", "importance_score": 0, "annotation_type": "is_occluded", "annotations": [{"annotation_id": "gCf1Q7hI", "annotator_id": "schne", "annotator_type": "human", "annotation_vector": [0, 1], "is_other": "", "annotation_type": "is_occluded"}]}, "is_truncated": {"group_id": "3", "importance_score": 1, "annotation_type": "is_truncated", "annotations": []}, "segment_type": {"group_id": "4", "importance_score": 0, "annotation_type": "segment_type", "annotations": [{"annotation_id": "pUxhhyVt", "annotator_id": "schne", "annotator_type": "human", "annotation_vector": [1, 0, 0, 0], "is_other": "", "annotation_type": "segment_type"}]}}, "child_segments": []}, {"segment_id": "EU8saAwB", "annotation_groups": {"segment_boundary": {"group_id": "0", "importance_score": 0, "annotation_type": "segment_boundary", "annotations": [{"annotation_id": "TMWtQ5Zv", "annotator_id": "bbu", "annotator_type": "human", "annotation_vector": [0.09756447228271904, 0.0780746860421998, 0.8935456948620815, 0.8684802705106561], "is_other": "", "annotation_type": "segment_boundary"}]}, "segment_label": {"group_id": "1", "importance_score": 0, "annotation_type": "segment_label", "annotations": [{"annotation_id": "UeiJYdJh", "annotator_id": "bbu", "annotator_type": "human", "annotation_vector": [0, 0, 0, 0, 0, 0, 0, 0, 0, 0], "is_other": "Auflistung", "annotation_type": "segment_label"}]}, "is_occluded": {"group_id": "2", "importance_score": 0, "annotation_type": "is_occluded", "annotations": [{"annotation_id": "dt2Wqol5", "annotator_id": "bbu", "annotator_type": "human", "annotation_vector": [0, 1], "is_other": "", "annotation_type": "is_occluded"}]}, "is_truncated": {"group_id": "3", "importance_score": 1, "annotation_type": "is_truncated", "annotations": []}, "segment_type": {"group_id": "4", "importance_score": 0, "annotation_type": "segment_type", "annotations": [{"annotation_id": "2x40uHaC", "annotator_id": "bbu", "annotator_type": "human", "annotation_vector": [1, 0, 0, 0], "is_other": "", "annotation_type": "segment_type"}]}}, "child_segments": []}]}, {"page_number": 3, "segments": [{"segment_id": "tCSQofrw", "annotation_groups": {"segment_boundary": {"group_id": "0", "importance_score": 0, "annotation_type": "segment_boundary", "annotations": [{"annotation_id": "aZd39ZD2", "annotator_id": "schne", "annotator_type": "human", "annotation_vector": [0.07334747497253291, 0.06444085861527554, 0.8939223512277449, 0.3561750563462318], "is_other": "", "annotation_type": "segment_boundary"}]}, "segment_label": {"group_id": "1", "importance_score": 0, "annotation_type": "segment_label", "annotations": [{"annotation_id": "pbRO5sBg", "annotator_id": "schne", "annotator_type": "human", "annotation_vector": [0, 0, 0, 0, 0, 0, 0, 0, 0, 0], "is_other": "is_other", "annotation_type": "segment_label"}]}, "is_occluded": {"group_id": "2", "importance_score": 0, "annotation_type": "is_occluded", "annotations": [{"annotation_id": "e3yszvMi", "annotator_id": "schne", "annotator_type": "human", "annotation_vector": [0, 1], "is_other": "", "annotation_type": "is_occluded"}]}, "is_truncated": {"group_id": "3", "importance_score": 1, "annotation_type": "is_truncated", "annotations": []}, "segment_type": {"group_id": "4", "importance_score": 0, "annotation_type": "segment_type", "annotations": [{"annotation_id": "YGoip2ut", "annotator_id": "schne", "annotator_type": "human", "annotation_vector": [1, 0, 0, 0], "is_other": "", "annotation_type": "segment_type"}]}}, "child_segments": []}, {"segment_id": "aRYlzSFb", "annotation_groups": {"segment_boundary": {"group_id": "0", "importance_score": 0, "annotation_type": "segment_boundary", "annotations": [{"annotation_id": "kW3IqdxY", "annotator_id": "bbu", "annotator_type": "human", "annotation_vector": [0.11348409673430634, 0.07936250854603927, 0.9026426231201315, 0.34658720716470276], "is_other": "", "annotation_type": "segment_boundary"}]}, "segment_label": {"group_id": "1", "importance_score": 0, "annotation_type": "segment_label", "annotations": [{"annotation_id": "XOnFX2Cz", "annotator_id": "bbu", "annotator_type": "human", "annotation_vector": [0, 0, 0, 0, 0, 0, 0, 0, 0, 0], "is_other": "Auflistung", "annotation_type": "segment_label"}]}, "is_occluded": {"group_id": "2", "importance_score": 0, "annotation_type": "is_occluded", "annotations": [{"annotation_id": "2volCBmx", "annotator_id": "bbu", "annotator_type": "human", "annotation_vector": [0, 1], "is_other": "", "annotation_type": "is_occluded"}]}, "is_truncated": {"group_id": "3", "importance_score": 1, "annotation_type": "is_truncated", "annotations": []}, "segment_type": {"group_id": "4", "importance_score": 0, "annotation_type": "segment_type", "annotations": [{"annotation_id": "19IdHA3z", "annotator_id": "bbu", "annotator_type": "human", "annotation_vector": [1, 0, 0, 0], "is_other": "", "annotation_type": "segment_type"}]}}, "child_segments": []}, {"segment_id": "x2o63nJV", "annotation_groups": {"segment_boundary": {"group_id": "0", "importance_score": 0, "annotation_type": "segment_boundary", "annotations": [{"annotation_id": "g5I440TH", "annotator_id": "bbu", "annotator_type": "human", "annotation_vector": [0.1157583287988188, 0.3675144425986945, 0.9003683910556189, 0.5574693488456961], "is_other": "", "annotation_type": "segment_boundary"}]}, "segment_label": {"group_id": "1", "importance_score": 0, "annotation_type": "segment_label", "annotations": [{"annotation_id": "A355MmXc", "annotator_id": "bbu", "annotator_type": "human", "annotation_vector": [0, 0, 0, 0, 0, 0, 0, 0, 0, 0], "is_other": "is_other", "annotation_type": "segment_label"}]}, "is_occluded": {"group_id": "2", "importance_score": 0, "annotation_type": "is_occluded", "annotations": [{"annotation_id": "rptlaugC", "annotator_id": "bbu", "annotator_type": "human", "annotation_vector": [0, 1], "is_other": "", "annotation_type": "is_occluded"}]}, "is_truncated": {"group_id": "3", "importance_score": 1, "annotation_type": "is_truncated", "annotations": []}, "segment_type": {"group_id": "4", "importance_score": 0, "annotation_type": "segment_type", "annotations": [{"annotation_id": "wPUydjcZ", "annotator_id": "bbu", "annotator_type": "human", "annotation_vector": [1, 0, 0, 0], "is_other": "", "annotation_type": "segment_type"}]}}, "child_segments": []}]}, {"page_number": -1, "segments": [{"segment_id": "1QIi2lYI", "annotation_groups": {"segment_boundary": {"group_id": "0", "importance_score": 0, "annotation_type": "segment_boundary", "annotations": [{"annotation_id": "4zRNvxhf", "annotator_id": "bbu", "annotator_type": "human", "annotation_vector": [-1, -1, -2, -2], "is_other": "", "annotation_type": "segment_boundary"}]}, "segment_label": {"group_id": "1", "importance_score": 0, "annotation_type": "segment_label", "annotations": [{"annotation_id": "lADITlkH", "annotator_id": "bbu", "annotator_type": "human", "annotation_vector": [0, 1, 0, 0, 0, 0, 0, 0, 0, 0], "is_other": "", "annotation_type": "segment_label"}]}, "is_occluded": {"group_id": "2", "importance_score": 0, "annotation_type": "is_occluded", "annotations": []}, "is_truncated": {"group_id": "3", "importance_score": 0, "annotation_type": "is_truncated", "annotations": []}, "segment_type": {"group_id": "4", "importance_score": 0, "annotation_type": "segment_type", "annotations": []}}, "child_segments": []}, {"segment_id": "UKaoG2iV", "annotation_groups": {"segment_boundary": {"group_id": "0", "importance_score": 0, "annotation_type": "segment_boundary", "annotations": [{"annotation_id": "ENJVcWEv", "annotator_id": "bbu", "annotator_type": "human", "annotation_vector": [-1, -1, -2, -2], "is_other": "", "annotation_type": "segment_boundary"}]}, "segment_label": {"group_id": "1", "importance_score": 0, "annotation_type": "segment_label", "annotations": [{"annotation_id": "m6ZKFqwI", "annotator_id": "bbu", "annotator_type": "human", "annotation_vector": [0, 0, 1, 0, 0, 0, 0, 0, 0, 0], "is_other": "", "annotation_type": "segment_label"}]}, "is_occluded": {"group_id": "2", "importance_score": 0, "annotation_type": "is_occluded", "annotations": []}, "is_truncated": {"group_id": "3", "importance_score": 0, "annotation_type": "is_truncated", "annotations": []}, "segment_type": {"group_id": "4", "importance_score": 0, "annotation_type": "segment_type", "annotations": []}}, "child_segments": []}, {"segment_id": "XdjrdbI9", "annotation_groups": {"segment_boundary": {"group_id": "0", "importance_score": 0, "annotation_type": "segment_boundary", "annotations": [{"annotation_id": "Gz217hm1", "annotator_id": "bbu", "annotator_type": "human", "annotation_vector": [-1, -1, -2, -2], "is_other": "", "annotation_type": "segment_boundary"}]}, "segment_label": {"group_id": "1", "importance_score": 0, "annotation_type": "segment_label", "annotations": [{"annotation_id": "iUDmYSCg", "annotator_id": "bbu", "annotator_type": "human", "annotation_vector": [0, 0, 0, 1, 0, 0, 0, 0, 0, 0], "is_other": "", "annotation_type": "segment_label"}]}, "is_occluded": {"group_id": "2", "importance_score": 0, "annotation_type": "is_occluded", "annotations": []}, "is_truncated": {"group_id": "3", "importance_score": 0, "annotation_type": "is_truncated", "annotations": []}, "segment_type": {"group_id": "4", "importance_score": 0, "annotation_type": "segment_type", "annotations": []}}, "child_segments": []}, {"segment_id": "mrCa39Gx", "annotation_groups": {"segment_boundary": {"group_id": "0", "importance_score": 0, "annotation_type": "segment_boundary", "annotations": [{"annotation_id": "Z1FxFOFq", "annotator_id": "bbu", "annotator_type": "human", "annotation_vector": [-1, -1, -2, -2], "is_other": "", "annotation_type": "segment_boundary"}]}, "segment_label": {"group_id": "1", "importance_score": 0, "annotation_type": "segment_label", "annotations": [{"annotation_id": "Lybdq5ae", "annotator_id": "bbu", "annotator_type": "human", "annotation_vector": [0, 0, 0, 0, 1, 0, 0, 0, 0, 0], "is_other": "", "annotation_type": "segment_label"}]}, "is_occluded": {"group_id": "2", "importance_score": 0, "annotation_type": "is_occluded", "annotations": []}, "is_truncated": {"group_id": "3", "importance_score": 0, "annotation_type": "is_truncated", "annotations": []}, "segment_type": {"group_id": "4", "importance_score": 0, "annotation_type": "segment_type", "annotations": []}}, "child_segments": []}, {"segment_id": "KoMw8cAp", "annotation_groups": {"segment_boundary": {"group_id": "0", "importance_score": 0, "annotation_type": "segment_boundary", "annotations": [{"annotation_id": "82aYKs5t", "annotator_id": "bbu", "annotator_type": "human", "annotation_vector": [-1, -1, -2, -2], "is_other": "", "annotation_type": "segment_boundary"}]}, "segment_label": {"group_id": "1", "importance_score": 0, "annotation_type": "segment_label", "annotations": [{"annotation_id": "fjzw6uSG", "annotator_id": "bbu", "annotator_type": "human", "annotation_vector": [0, 0, 0, 0, 0, 1, 0, 0, 0, 0], "is_other": "", "annotation_type": "segment_label"}]}, "is_occluded": {"group_id": "2", "importance_score": 0, "annotation_type": "is_occluded", "annotations": []}, "is_truncated": {"group_id": "3", "importance_score": 0, "annotation_type": "is_truncated", "annotations": []}, "segment_type": {"group_id": "4", "importance_score": 0, "annotation_type": "segment_type", "annotations": []}}, "child_segments": []}, {"segment_id": "OoQVoEOK", "annotation_groups": {"segment_boundary": {"group_id": "0", "importance_score": 0, "annotation_type": "segment_boundary", "annotations": [{"annotation_id": "C5VpX43W", "annotator_id": "bbu", "annotator_type": "human", "annotation_vector": [-1, -1, -2, -2], "is_other": "", "annotation_type": "segment_boundary"}]}, "segment_label": {"group_id": "1", "importance_score": 0, "annotation_type": "segment_label", "annotations": [{"annotation_id": "upbpu6SW", "annotator_id": "bbu", "annotator_type": "human", "annotation_vector": [0, 0, 0, 0, 0, 0, 1, 0, 0, 0], "is_other": "", "annotation_type": "segment_label"}]}, "is_occluded": {"group_id": "2", "importance_score": 0, "annotation_type": "is_occluded", "annotations": []}, "is_truncated": {"group_id": "3", "importance_score": 0, "annotation_type": "is_truncated", "annotations": []}, "segment_type": {"group_id": "4", "importance_score": 0, "annotation_type": "segment_type", "annotations": []}}, "child_segments": []}, {"segment_id": "x0nWk9EC", "annotation_groups": {"segment_boundary": {"group_id": "0", "importance_score": 0, "annotation_type": "segment_boundary", "annotations": [{"annotation_id": "pQeOgmxl", "annotator_id": "bbu", "annotator_type": "human", "annotation_vector": [-1, -1, -2, -2], "is_other": "", "annotation_type": "segment_boundary"}]}, "segment_label": {"group_id": "1", "importance_score": 0, "annotation_type": "segment_label", "annotations": [{"annotation_id": "o2nXmgNY", "annotator_id": "bbu", "annotator_type": "human", "annotation_vector": [0, 0, 0, 0, 0, 0, 0, 1, 0, 0], "is_other": "", "annotation_type": "segment_label"}]}, "is_occluded": {"group_id": "2", "importance_score": 0, "annotation_type": "is_occluded", "annotations": []}, "is_truncated": {"group_id": "3", "importance_score": 0, "annotation_type": "is_truncated", "annotations": []}, "segment_type": {"group_id": "4", "importance_score": 0, "annotation_type": "segment_type", "annotations": []}}, "child_segments": []}, {"segment_id": "ovSCUxGd", "annotation_groups": {"segment_boundary": {"group_id": "0", "importance_score": 0, "annotation_type": "segment_boundary", "annotations": [{"annotation_id": "issGGOof", "annotator_id": "bbu", "annotator_type": "human", "annotation_vector": [-1, -1, -2, -2], "is_other": "", "annotation_type": "segment_boundary"}]}, "segment_label": {"group_id": "1", "importance_score": 0, "annotation_type": "segment_label", "annotations": [{"annotation_id": "jMeESo6l", "annotator_id": "bbu", "annotator_type": "human", "annotation_vector": [0, 0, 0, 0, 0, 0, 0, 0, 1, 0], "is_other": "", "annotation_type": "segment_label"}]}, "is_occluded": {"group_id": "2", "importance_score": 0, "annotation_type": "is_occluded", "annotations": []}, "is_truncated": {"group_id": "3", "importance_score": 0, "annotation_type": "is_truncated", "annotations": []}, "segment_type": {"group_id": "4", "importance_score": 0, "annotation_type": "segment_type", "annotations": []}}, "child_segments": []}, {"segment_id": "uFJmO22Q", "annotation_groups": {"segment_boundary": {"group_id": "0", "importance_score": 0, "annotation_type": "segment_boundary", "annotations": [{"annotation_id": "dp5qXjzv", "annotator_id": "bbu", "annotator_type": "human", "annotation_vector": [-1, -1, -2, -2], "is_other": "", "annotation_type": "segment_boundary"}]}, "segment_label": {"group_id": "1", "importance_score": 0, "annotation_type": "segment_label", "annotations": []}, "is_occluded": {"group_id": "2", "importance_score": 0, "annotation_type": "is_occluded", "annotations": []}, "is_truncated": {"group_id": "3", "importance_score": 0, "annotation_type": "is_truncated", "annotations": []}, "segment_type": {"group_id": "4", "importance_score": 0, "annotation_type": "segment_type", "annotations": [{"annotation_id": "yKBLKjRj", "annotator_id": "bbu", "annotator_type": "human", "annotation_vector": [0, 1, 0, 0], "is_other": "", "annotation_type": "segment_type"}]}}, "child_segments": []}, {"segment_id": "OF1pVgJv", "annotation_groups": {"segment_boundary": {"group_id": "0", "importance_score": 0, "annotation_type": "segment_boundary", "annotations": [{"annotation_id": "LWJo8Q9o", "annotator_id": "bbu", "annotator_type": "human", "annotation_vector": [-1, -1, -2, -2], "is_other": "", "annotation_type": "segment_boundary"}]}, "segment_label": {"group_id": "1", "importance_score": 0, "annotation_type": "segment_label", "annotations": []}, "is_occluded": {"group_id": "2", "importance_score": 0, "annotation_type": "is_occluded", "annotations": []}, "is_truncated": {"group_id": "3", "importance_score": 0, "annotation_type": "is_truncated", "annotations": []}, "segment_type": {"group_id": "4", "importance_score": 0, "annotation_type": "segment_type", "annotations": [{"annotation_id": "E6nfV4TX", "annotator_id": "bbu", "annotator_type": "human", "annotation_vector": [0, 0, 1, 0], "is_other": "", "annotation_type": "segment_type"}]}}, "child_segments": []}, {"segment_id": "yWIug6rC", "annotation_groups": {"segment_boundary": {"group_id": "0", "importance_score": 0, "annotation_type": "segment_boundary", "annotations": [{"annotation_id": "MAVnuPd8", "annotator_id": "bbu", "annotator_type": "human", "annotation_vector": [-1, -1, -2, -2], "is_other": "", "annotation_type": "segment_boundary"}]}, "segment_label": {"group_id": "1", "importance_score": 0, "annotation_type": "segment_label", "annotations": []}, "is_occluded": {"group_id": "2", "importance_score": 0, "annotation_type": "is_occluded", "annotations": []}, "is_truncated": {"group_id": "3", "importance_score": 0, "annotation_type": "is_truncated", "annotations": []}, "segment_type": {"group_id": "4", "importance_score": 0, "annotation_type": "segment_type", "annotations": [{"annotation_id": "6KgBl128", "annotator_id": "bbu", "annotator_type": "human", "annotation_vector": [0, 0, 0, 1], "is_other": "", "annotation_type": "segment_type"}]}}, "child_segments": []}]}], "annotated_by": {"document_contains": [{"name": "AleX", "timestamp": "2020-04-21T12:00:00.000Z"}], "document_label": [{"name": "AleX", "timestamp": "2020-04-21T12:00:00.000Z"}], "document_type": [{"name": "AleX", "timestamp": "2020-04-21T12:00:00.000Z"}], "is_occluded": [{"name": "schne", "timestamp": "2020-04-21T12:00:00.000Z"}, {"name": "bbu", "timestamp": "2020-06-03T08:41:44.490Z"}], "is_truncated": [], "segment_boundary": [{"name": "schne", "timestamp": "2020-04-21T12:00:00.000Z"}, {"name": "bbu", "timestamp": "2020-06-03T08:40:28.862Z"}], "segment_label": [{"name": "schne", "timestamp": "2020-04-21T12:00:00.000Z"}, {"name": "schne", "timestamp": "2020-04-21T12:00:00.000Z"}, {"name": "bbu", "timestamp": "2020-06-03T08:40:28.862Z"}, {"name": "bbu", "timestamp": "2020-06-03T08:41:44.490Z"}], "segment_type": [{"name": "schne", "timestamp": "2020-04-21T12:00:00.000Z"}, {"name": "schne", "timestamp": "2020-04-21T12:00:00.000Z"}, {"name": "bbu", "timestamp": "2020-06-03T08:40:28.862Z"}, {"name": "bbu", "timestamp": "2020-06-03T08:41:44.490Z"}]}, "annotation_completion": "complete", "target_collection": "total_annotation"}