{"document_id": "d6f5e4e11e4db20cfb8d00c738a6b8b2", "importance_score": 8.376000000000001, "initial_importance": 1, "origin": "SynthetischerFall", "document_label": {"group_id": "0", "importance_score": 0, "annotation_type": "document_label", "annotations": [{"annotation_id": "0", "annotator_id": "folder_model", "annotator_type": "model", "annotation_vector": [1, 0, 0, 0, 0, 0, 0, 0, 0, 0, 0, 0, 0, 0, 0, 0, 0, 0, 0], "is_other": "", "annotation_type": "document_label"}, {"annotation_id": "O5VSjB5o", "annotator_id": "Flossi", "annotator_type": "human", "annotation_vector": [1, 0, 0, 0, 0, 0, 0, 0, 0, 0, 0, 0, 0, 0, 0, 0, 0, 0, 0], "is_other": "", "annotation_type": "document_label"}]}, "document_type": {"group_id": "1", "importance_score": 0, "annotation_type": "document_type", "annotations": [{"annotation_id": "PuKQnM8R", "annotator_id": "Flossi", "annotator_type": "human", "annotation_vector": [1, 0, 0], "is_other": "", "annotation_type": "document_type"}]}, "document_contains": {"group_id": "2", "importance_score": 0, "annotation_type": "document_contains", "annotations": [{"annotation_id": "XEu1AKQT", "annotator_id": "Flossi", "annotator_type": "human", "annotation_vector": [1, 0, 1, 1, 1, 0, 0, 0, 0, 1, 1, 1, 1, 0], "is_other": "", "annotation_type": "document_contains"}, {"annotation_id": "IcMuQ7gx", "annotator_id": "anonymous_L8eBD", "annotator_type": "human", "annotation_vector": [1, 1, 1, 1, 1, 1, 1, 1, 1, 1, 1, 1, 1, 1], "is_other": "", "annotation_type": "document_contains"}]}, "pages": [{"page_number": 0, "segments": [{"segment_id": "kUJcRnHq", "annotation_groups": {"segment_boundary": {"group_id": "0", "importance_score": 0, "annotation_type": "segment_boundary", "annotations": [{"annotation_id": "l4miEK9V", "annotator_id": "Dominik", "annotator_type": "human", "annotation_vector": [0.11112234590050617, 0.23804206804757225, 0.2860613402304029, 0.35888560983072926], "is_other": "", "annotation_type": "segment_boundary"}]}, "segment_label": {"group_id": "1", "importance_score": 0, "annotation_type": "segment_label", "annotations": [{"annotation_id": "v5IqTE36", "annotator_id": "Dominik", "annotator_type": "human", "annotation_vector": [1, 0, 0, 0, 0, 0, 0, 0, 0, 0], "is_other": "", "annotation_type": "segment_label"}]}, "is_occluded": {"group_id": "2", "importance_score": 0, "annotation_type": "is_occluded", "annotations": [{"annotation_id": "pNIqD2fj", "annotator_id": "Dominik", "annotator_type": "human", "annotation_vector": [0, 1], "is_other": "", "annotation_type": "is_occluded"}]}, "is_truncated": {"group_id": "3", "importance_score": 1, "annotation_type": "is_truncated", "annotations": []}, "segment_type": {"group_id": "4", "importance_score": 0, "annotation_type": "segment_type", "annotations": [{"annotation_id": "wayyuh38", "annotator_id": "Dominik", "annotator_type": "human", "annotation_vector": [1, 0, 0, 0], "is_other": "", "annotation_type": "segment_type"}]}}, "child_segments": []}, {"segment_id": "7VwZP9eP", "annotation_groups": {"segment_boundary": {"group_id": "0", "importance_score": 0, "annotation_type": "segment_boundary", "annotations": [{"annotation_id": "0wOSMl9p", "annotator_id": "Dominik", "annotator_type": "human", "annotation_vector": [0.04498687243432569, 0.04469240119452099, 0.9815505128102363, 0.22746825814154598], "is_other": "", "annotation_type": "segment_boundary"}]}, "segment_label": {"group_id": "1", "importance_score": 0, "annotation_type": "segment_label", "annotations": [{"annotation_id": "PZD65bp1", "annotator_id": "Dominik", "annotator_type": "human", "annotation_vector": [0, 0, 1, 0, 0, 0, 0, 0, 0, 0], "is_other": "", "annotation_type": "segment_label"}]}, "is_occluded": {"group_id": "2", "importance_score": 0, "annotation_type": "is_occluded", "annotations": [{"annotation_id": "tlY04iFw", "annotator_id": "Dominik", "annotator_type": "human", "annotation_vector": [0, 1], "is_other": "", "annotation_type": "is_occluded"}]}, "is_truncated": {"group_id": "3", "importance_score": 1, "annotation_type": "is_truncated", "annotations": []}, "segment_type": {"group_id": "4", "importance_score": 0, "annotation_type": "segment_type", "annotations": [{"annotation_id": "4dlcptdk", "annotator_id": "Dominik", "annotator_type": "human", "annotation_vector": [0, 0, 0, 0], "is_other": "is_other", "annotation_type": "segment_type"}]}}, "child_segments": []}, {"segment_id": "1zELoHlb", "annotation_groups": {"segment_boundary": {"group_id": "0", "importance_score": 0, "annotation_type": "segment_boundary", "annotations": [{"annotation_id": "YIDiX3SL", "annotator_id": "Dominik", "annotator_type": "human", "annotation_vector": [0.07698790798247754, 0.9087237249440938, 0.9516828796319612, 0.9766982171971196], "is_other": "", "annotation_type": "segment_boundary"}]}, "segment_label": {"group_id": "1", "importance_score": 0, "annotation_type": "segment_label", "annotations": [{"annotation_id": "VY7LIhed", "annotator_id": "Dominik", "annotator_type": "human", "annotation_vector": [0, 0, 0, 1, 0, 0, 0, 0, 0, 0], "is_other": "", "annotation_type": "segment_label"}]}, "is_occluded": {"group_id": "2", "importance_score": 0, "annotation_type": "is_occluded", "annotations": [{"annotation_id": "zcrEhp8I", "annotator_id": "Dominik", "annotator_type": "human", "annotation_vector": [0, 1], "is_other": "", "annotation_type": "is_occluded"}]}, "is_truncated": {"group_id": "3", "importance_score": 1, "annotation_type": "is_truncated", "annotations": []}, "segment_type": {"group_id": "4", "importance_score": 0, "annotation_type": "segment_type", "annotations": [{"annotation_id": "xWwwYRvR", "annotator_id": "Dominik", "annotator_type": "human", "annotation_vector": [1, 0, 0, 0], "is_other": "", "annotation_type": "segment_type"}]}}, "child_segments": []}, {"segment_id": "dGVtDkPH", "annotation_groups": {"segment_boundary": {"group_id": "0", "importance_score": 0, "annotation_type": "segment_boundary", "annotations": [{"annotation_id": "ZMolO1Y6", "annotator_id": "Dominik", "annotator_type": "human", "annotation_vector": [0.264728065394825, 0.07188219809573126, 0.708475009466007, 0.20631289631987193], "is_other": "", "annotation_type": "segment_boundary"}]}, "segment_label": {"group_id": "1", "importance_score": 0, "annotation_type": "segment_label", "annotations": [{"annotation_id": "ctYMiEnq", "annotator_id": "Dominik", "annotator_type": "human", "annotation_vector": [0, 0, 0, 0, 1, 0, 0, 0, 0, 0], "is_other": "", "annotation_type": "segment_label"}]}, "is_occluded": {"group_id": "2", "importance_score": 0, "annotation_type": "is_occluded", "annotations": [{"annotation_id": "jJRd5tfB", "annotator_id": "Dominik", "annotator_type": "human", "annotation_vector": [0, 1], "is_other": "", "annotation_type": "is_occluded"}]}, "is_truncated": {"group_id": "3", "importance_score": 1, "annotation_type": "is_truncated", "annotations": []}, "segment_type": {"group_id": "4", "importance_score": 0, "annotation_type": "segment_type", "annotations": [{"annotation_id": "NmazYaiP", "annotator_id": "Dominik", "annotator_type": "human", "annotation_vector": [0, 0, 0, 0], "is_other": "is_other", "annotation_type": "segment_type"}]}}, "child_segments": []}, {"segment_id": "zl0uDJ2g", "annotation_groups": {"segment_boundary": {"group_id": "0", "importance_score": 0, "annotation_type": "segment_boundary", "annotations": [{"annotation_id": "98TkNhTv", "annotator_id": "Dominik", "annotator_type": "human", "annotation_vector": [0.1196559553800133, 0.2712740420379404, 0.27539432838101896, 0.34529071138012407], "is_other": "", "annotation_type": "segment_boundary"}]}, "segment_label": {"group_id": "1", "importance_score": 0, "annotation_type": "segment_label", "annotations": [{"annotation_id": "OMCgmX1x", "annotator_id": "Dominik", "annotator_type": "human", "annotation_vector": [0, 0, 0, 0, 0, 0, 0, 0, 0, 1], "is_other": "", "annotation_type": "segment_label"}]}, "is_occluded": {"group_id": "2", "importance_score": 0, "annotation_type": "is_occluded", "annotations": [{"annotation_id": "TjD3scaA", "annotator_id": "Dominik", "annotator_type": "human", "annotation_vector": [0, 1], "is_other": "", "annotation_type": "is_occluded"}]}, "is_truncated": {"group_id": "3", "importance_score": 1, "annotation_type": "is_truncated", "annotations": []}, "segment_type": {"group_id": "4", "importance_score": 0, "annotation_type": "segment_type", "annotations": [{"annotation_id": "PPpaiIr1", "annotator_id": "Dominik", "annotator_type": "human", "annotation_vector": [1, 0, 0, 0], "is_other": "", "annotation_type": "segment_type"}]}}, "child_segments": []}, {"segment_id": "DCof0cWH", "annotation_groups": {"segment_boundary": {"group_id": "0", "importance_score": 0, "annotation_type": "segment_boundary", "annotations": [{"annotation_id": "98YFaWOh", "annotator_id": "Dominik", "annotator_type": "human", "annotation_vector": [0.1047221387908758, 0.3830543181873607, 0.8578131753573824, 0.6428679330211484], "is_other": "", "annotation_type": "segment_boundary"}]}, "segment_label": {"group_id": "1", "importance_score": 0, "annotation_type": "segment_label", "annotations": [{"annotation_id": "2gvGyhJJ", "annotator_id": "Dominik", "annotator_type": "human", "annotation_vector": [0, 0, 0, 0, 0, 0, 0, 0, 0, 0], "is_other": "Leistungsgegenstand", "annotation_type": "segment_label"}]}, "is_occluded": {"group_id": "2", "importance_score": 0, "annotation_type": "is_occluded", "annotations": [{"annotation_id": "p4aguvAm", "annotator_id": "Dominik", "annotator_type": "human", "annotation_vector": [0, 1], "is_other": "", "annotation_type": "is_occluded"}]}, "is_truncated": {"group_id": "3", "importance_score": 1, "annotation_type": "is_truncated", "annotations": []}, "segment_type": {"group_id": "4", "importance_score": 0, "annotation_type": "segment_type", "annotations": [{"annotation_id": "SPvb6Mkn", "annotator_id": "Dominik", "annotator_type": "human", "annotation_vector": [1, 0, 0, 0], "is_other": "", "annotation_type": "segment_type"}]}}, "child_segments": []}, {"segment_id": "hLzRH83w", "annotation_groups": {"segment_boundary": {"group_id": "0", "importance_score": 0, "annotation_type": "segment_boundary", "annotations": [{"annotation_id": "LRHlxxvN", "annotator_id": "Dominik", "annotator_type": "human", "annotation_vector": [0.2689941212713886, 0.08245600800175756, 0.7020748023563769, 0.17913084142828317], "is_other": "", "annotation_type": "segment_boundary"}]}, "segment_label": {"group_id": "1", "importance_score": 0, "annotation_type": "segment_label", "annotations": [{"annotation_id": "Vighu3tX", "annotator_id": "Dominik", "annotator_type": "human", "annotation_vector": [0, 0, 0, 0, 1, 0, 0, 0, 0, 0], "is_other": "", "annotation_type": "segment_label"}]}, "is_occluded": {"group_id": "2", "importance_score": 0, "annotation_type": "is_occluded", "annotations": [{"annotation_id": "9Sea0nhO", "annotator_id": "Dominik", "annotator_type": "human", "annotation_vector": [0, 1], "is_other": "", "annotation_type": "is_occluded"}]}, "is_truncated": {"group_id": "3", "importance_score": 1, "annotation_type": "is_truncated", "annotations": []}, "segment_type": {"group_id": "4", "importance_score": 0, "annotation_type": "segment_type", "annotations": [{"annotation_id": "2FfhZsUl", "annotator_id": "Dominik", "annotator_type": "human", "annotation_vector": [0, 1, 0, 0], "is_other": "", "annotation_type": "segment_type"}]}}, "child_segments": []}, {"segment_id": "GZBxXXA4", "annotation_groups": {"segment_boundary": {"group_id": "0", "importance_score": 0, "annotation_type": "segment_boundary", "annotations": [{"annotation_id": "U4SR1fHE", "annotator_id": "Dominik", "annotator_type": "human", "annotation_vector": [0.11325574827038296, 0.6428679330211483, 0.8898142109055344, 0.7637114748043053], "is_other": "", "annotation_type": "segment_boundary"}]}, "segment_label": {"group_id": "1", "importance_score": 0, "annotation_type": "segment_label", "annotations": [{"annotation_id": "MPxFkWKy", "annotator_id": "Dominik", "annotator_type": "human", "annotation_vector": [0, 0, 0, 0, 0, 0, 0, 0, 0, 0], "is_other": "Kalkulation", "annotation_type": "segment_label"}]}, "is_occluded": {"group_id": "2", "importance_score": 0, "annotation_type": "is_occluded", "annotations": [{"annotation_id": "s171D5lx", "annotator_id": "Dominik", "annotator_type": "human", "annotation_vector": [0, 1], "is_other": "", "annotation_type": "is_occluded"}]}, "is_truncated": {"group_id": "3", "importance_score": 1, "annotation_type": "is_truncated", "annotations": []}, "segment_type": {"group_id": "4", "importance_score": 0, "annotation_type": "segment_type", "annotations": [{"annotation_id": "X8zbi34E", "annotator_id": "Dominik", "annotator_type": "human", "annotation_vector": [0, 0, 1, 0], "is_other": "", "annotation_type": "segment_type"}]}}, "child_segments": []}, {"segment_id": "omdmiXtx", "annotation_groups": {"segment_boundary": {"group_id": "0", "importance_score": 0, "annotation_type": "segment_boundary", "annotations": [{"annotation_id": "nq5JCyPb", "annotator_id": "ziebermayr", "annotator_type": "human", "annotation_vector": [0.0958419548909245, 0.2412157960199005, 0.31214581638787336, 0.35066853233830847], "is_other": "", "annotation_type": "segment_boundary"}]}, "segment_label": {"group_id": "1", "importance_score": 0, "annotation_type": "segment_label", "annotations": [{"annotation_id": "fbKCgcwt", "annotator_id": "ziebermayr", "annotator_type": "human", "annotation_vector": [1, 0, 0, 0, 0, 0, 0, 0, 0, 0], "is_other": "", "annotation_type": "segment_label"}]}, "is_occluded": {"group_id": "2", "importance_score": 0, "annotation_type": "is_occluded", "annotations": [{"annotation_id": "D4IVKaaR", "annotator_id": "ziebermayr", "annotator_type": "human", "annotation_vector": [0, 1], "is_other": "", "annotation_type": "is_occluded"}]}, "is_truncated": {"group_id": "3", "importance_score": 1, "annotation_type": "is_truncated", "annotations": []}, "segment_type": {"group_id": "4", "importance_score": 0, "annotation_type": "segment_type", "annotations": [{"annotation_id": "cGEIEz89", "annotator_id": "ziebermayr", "annotator_type": "human", "annotation_vector": [1, 0, 0, 0], "is_other": "", "annotation_type": "segment_type"}]}}, "child_segments": []}, {"segment_id": "OzxqWgru", "annotation_groups": {"segment_boundary": {"group_id": "0", "importance_score": 0, "annotation_type": "segment_boundary", "annotations": [{"annotation_id": "dWBrt4rC", "annotator_id": "ziebermayr", "annotator_type": "human", "annotation_vector": [0.10463479478917445, 0.9215640547263682, 0.9153346334078202, 0.9750466417910447], "is_other": "", "annotation_type": "segment_boundary"}]}, "segment_label": {"group_id": "1", "importance_score": 0, "annotation_type": "segment_label", "annotations": [{"annotation_id": "U8A1UFXi", "annotator_id": "ziebermayr", "annotator_type": "human", "annotation_vector": [0, 0, 0, 1, 0, 0, 0, 0, 0, 0], "is_other": "", "annotation_type": "segment_label"}]}, "is_occluded": {"group_id": "2", "importance_score": 0, "annotation_type": "is_occluded", "annotations": [{"annotation_id": "7oXafdDr", "annotator_id": "ziebermayr", "annotator_type": "human", "annotation_vector": [0, 1], "is_other": "", "annotation_type": "is_occluded"}]}, "is_truncated": {"group_id": "3", "importance_score": 1, "annotation_type": "is_truncated", "annotations": []}, "segment_type": {"group_id": "4", "importance_score": 0, "annotation_type": "segment_type", "annotations": [{"annotation_id": "xyj6eUw6", "annotator_id": "ziebermayr", "annotator_type": "human", "annotation_vector": [1, 0, 0, 0], "is_other": "", "annotation_type": "segment_type"}]}}, "child_segments": []}, {"segment_id": "puPbYMMI", "annotation_groups": {"segment_boundary": {"group_id": "0", "importance_score": 0, "annotation_type": "segment_boundary", "annotations": [{"annotation_id": "zAF3Rjpq", "annotator_id": "ziebermayr", "annotator_type": "human", "annotation_vector": [0.2523545050797737, 0.07454912935323384, 0.7254092916056212, 0.21260883084577115], "is_other": "", "annotation_type": "segment_boundary"}]}, "segment_label": {"group_id": "1", "importance_score": 0, "annotation_type": "segment_label", "annotations": [{"annotation_id": "EPPx3cK1", "annotator_id": "ziebermayr", "annotator_type": "human", "annotation_vector": [0, 0, 0, 0, 1, 0, 0, 0, 0, 0], "is_other": "", "annotation_type": "segment_label"}]}, "is_occluded": {"group_id": "2", "importance_score": 1, "annotation_type": "is_occluded", "annotations": []}, "is_truncated": {"group_id": "3", "importance_score": 1, "annotation_type": "is_truncated", "annotations": []}, "segment_type": {"group_id": "4", "importance_score": 1, "annotation_type": "segment_type", "annotations": []}}, "child_segments": []}, {"segment_id": "DWSM70gV", "annotation_groups": {"segment_boundary": {"group_id": "0", "importance_score": 0, "annotation_type": "segment_boundary", "annotations": [{"annotation_id": "Jj0JfKhk", "annotator_id": "ziebermayr", "annotator_type": "human", "annotation_vector": [0.09056625095197453, 0.29345460199004975, 0.27697445679487354, 0.3494247512437811], "is_other": "", "annotation_type": "segment_boundary"}]}, "segment_label": {"group_id": "1", "importance_score": 0, "annotation_type": "segment_label", "annotations": [{"annotation_id": "PLVlQFv8", "annotator_id": "ziebermayr", "annotator_type": "human", "annotation_vector": [0, 0, 0, 0, 0, 0, 0, 0, 0, 1], "is_other": "", "annotation_type": "segment_label"}]}, "is_occluded": {"group_id": "2", "importance_score": 0, "annotation_type": "is_occluded", "annotations": [{"annotation_id": "pyOZkpXK", "annotator_id": "ziebermayr", "annotator_type": "human", "annotation_vector": [0, 1], "is_other": "", "annotation_type": "is_occluded"}]}, "is_truncated": {"group_id": "3", "importance_score": 1, "annotation_type": "is_truncated", "annotations": []}, "segment_type": {"group_id": "4", "importance_score": 0, "annotation_type": "segment_type", "annotations": [{"annotation_id": "TyyRWeoI", "annotator_id": "ziebermayr", "annotator_type": "human", "annotation_vector": [1, 0, 0, 0], "is_other": "", "annotation_type": "segment_type"}]}}, "child_segments": []}, {"segment_id": "lQFFwyxS", "annotation_groups": {"segment_boundary": {"group_id": "0", "importance_score": 0, "annotation_type": "segment_boundary", "annotations": [{"annotation_id": "R4keWIXP", "annotator_id": "ziebermayr", "annotator_type": "human", "annotation_vector": [0.13804758640252426, 0.9190764925373134, 0.8590604580590204, 0.9638526119402985], "is_other": "", "annotation_type": "segment_boundary"}]}, "segment_label": {"group_id": "1", "importance_score": 0, "annotation_type": "segment_label", "annotations": [{"annotation_id": "9l9tGHem", "annotator_id": "ziebermayr", "annotator_type": "human", "annotation_vector": [0, 0, 0, 0, 0, 0, 0, 0, 0, 1], "is_other": "", "annotation_type": "segment_label"}]}, "is_occluded": {"group_id": "2", "importance_score": 0, "annotation_type": "is_occluded", "annotations": [{"annotation_id": "WYtmI9tq", "annotator_id": "ziebermayr", "annotator_type": "human", "annotation_vector": [0, 1], "is_other": "", "annotation_type": "is_occluded"}]}, "is_truncated": {"group_id": "3", "importance_score": 1, "annotation_type": "is_truncated", "annotations": []}, "segment_type": {"group_id": "4", "importance_score": 0, "annotation_type": "segment_type", "annotations": [{"annotation_id": "T0b2kJG0", "annotator_id": "ziebermayr", "annotator_type": "human", "annotation_vector": [1, 0, 0, 0], "is_other": "", "annotation_type": "segment_type"}]}}, "child_segments": []}, {"segment_id": "fQIuGRu2", "annotation_groups": {"segment_boundary": {"group_id": "0", "importance_score": 0, "annotation_type": "segment_boundary", "annotations": [{"annotation_id": "Ia8o9o8o", "annotator_id": "ziebermayr", "annotator_type": "human", "annotation_vector": [0.12046190660602436, 0.7984297263681592, 0.7043064758498213, 0.8332555970149254], "is_other": "", "annotation_type": "segment_boundary"}]}, "segment_label": {"group_id": "1", "importance_score": 0, "annotation_type": "segment_label", "annotations": [{"annotation_id": "2dvDr29h", "annotator_id": "ziebermayr", "annotator_type": "human", "annotation_vector": [0, 0, 0, 0, 0, 0, 0, 0, 0, 0], "is_other": "Abredefloskel", "annotation_type": "segment_label"}]}, "is_occluded": {"group_id": "2", "importance_score": 0, "annotation_type": "is_occluded", "annotations": [{"annotation_id": "DV9AlneZ", "annotator_id": "ziebermayr", "annotator_type": "human", "annotation_vector": [0, 1], "is_other": "", "annotation_type": "is_occluded"}]}, "is_truncated": {"group_id": "3", "importance_score": 1, "annotation_type": "is_truncated", "annotations": []}, "segment_type": {"group_id": "4", "importance_score": 0, "annotation_type": "segment_type", "annotations": [{"annotation_id": "CWpa02aB", "annotator_id": "ziebermayr", "annotator_type": "human", "annotation_vector": [1, 0, 0, 0], "is_other": "", "annotation_type": "segment_type"}]}}, "child_segments": []}, {"segment_id": "N8LKRSQQ", "annotation_groups": {"segment_boundary": {"group_id": "0", "importance_score": 0, "annotation_type": "segment_boundary", "annotations": [{"annotation_id": "LeqqX5TX", "annotator_id": "ziebermayr", "annotator_type": "human", "annotation_vector": [0.6550665724196215, 0.3208177860696517, 0.8080619866491707, 0.3481809701492537], "is_other": "", "annotation_type": "segment_boundary"}]}, "segment_label": {"group_id": "1", "importance_score": 0, "annotation_type": "segment_label", "annotations": [{"annotation_id": "QP9H96iQ", "annotator_id": "ziebermayr", "annotator_type": "human", "annotation_vector": [0, 0, 0, 0, 0, 0, 0, 0, 0, 0], "is_other": "Ort und Datum", "annotation_type": "segment_label"}]}, "is_occluded": {"group_id": "2", "importance_score": 0, "annotation_type": "is_occluded", "annotations": [{"annotation_id": "OK1Um8sd", "annotator_id": "ziebermayr", "annotator_type": "human", "annotation_vector": [0, 1], "is_other": "", "annotation_type": "is_occluded"}]}, "is_truncated": {"group_id": "3", "importance_score": 1, "annotation_type": "is_truncated", "annotations": []}, "segment_type": {"group_id": "4", "importance_score": 0, "annotation_type": "segment_type", "annotations": [{"annotation_id": "wbvA7nGa", "annotator_id": "ziebermayr", "annotator_type": "human", "annotation_vector": [1, 0, 0, 0], "is_other": "", "annotation_type": "segment_type"}]}}, "child_segments": []}, {"segment_id": "iR9aBfSK", "annotation_groups": {"segment_boundary": {"group_id": "0", "importance_score": 0, "annotation_type": "segment_boundary", "annotations": [{"annotation_id": "WO03QpOw", "annotator_id": "ziebermayr", "annotator_type": "human", "annotation_vector": [0.10815193074847443, 0.38051927860696516, 0.8907146816927203, 0.5670864427860697], "is_other": "", "annotation_type": "segment_boundary"}]}, "segment_label": {"group_id": "1", "importance_score": 0, "annotation_type": "segment_label", "annotations": [{"annotation_id": "cIPm2G5i", "annotator_id": "ziebermayr", "annotator_type": "human", "annotation_vector": [0, 0, 0, 0, 0, 0, 0, 0, 0, 0], "is_other": "Rechnungsinformation", "annotation_type": "segment_label"}]}, "is_occluded": {"group_id": "2", "importance_score": 0, "annotation_type": "is_occluded", "annotations": [{"annotation_id": "MQAnIQNQ", "annotator_id": "ziebermayr", "annotator_type": "human", "annotation_vector": [0, 1], "is_other": "", "annotation_type": "is_occluded"}]}, "is_truncated": {"group_id": "3", "importance_score": 1, "annotation_type": "is_truncated", "annotations": []}, "segment_type": {"group_id": "4", "importance_score": 0, "annotation_type": "segment_type", "annotations": [{"annotation_id": "SC1f7q5i", "annotator_id": "ziebermayr", "annotator_type": "human", "annotation_vector": [1, 0, 0, 0], "is_other": "", "annotation_type": "segment_type"}]}}, "child_segments": []}, {"segment_id": "pMK2RzPN", "annotation_groups": {"segment_boundary": {"group_id": "0", "importance_score": 0, "annotation_type": "segment_boundary", "annotations": [{"annotation_id": "6OYyuY2n", "annotator_id": "ziebermayr", "annotator_type": "human", "annotation_vector": [0.09056625095197453, 0.6168376865671642, 0.7342021315038711, 0.6429570895522388], "is_other": "", "annotation_type": "segment_boundary"}]}, "segment_label": {"group_id": "1", "importance_score": 0, "annotation_type": "segment_label", "annotations": [{"annotation_id": "WK6BuUaj", "annotator_id": "ziebermayr", "annotator_type": "human", "annotation_vector": [0, 0, 0, 0, 0, 0, 0, 0, 0, 0], "is_other": "Rechnungsinformation", "annotation_type": "segment_label"}]}, "is_occluded": {"group_id": "2", "importance_score": 0, "annotation_type": "is_occluded", "annotations": [{"annotation_id": "bxNKDQkw", "annotator_id": "ziebermayr", "annotator_type": "human", "annotation_vector": [0, 1], "is_other": "", "annotation_type": "is_occluded"}]}, "is_truncated": {"group_id": "3", "importance_score": 1, "annotation_type": "is_truncated", "annotations": []}, "segment_type": {"group_id": "4", "importance_score": 0, "annotation_type": "segment_type", "annotations": [{"annotation_id": "A9hr2Efs", "annotator_id": "ziebermayr", "annotator_type": "human", "annotation_vector": [1, 0, 0, 0], "is_other": "", "annotation_type": "segment_type"}]}}, "child_segments": []}, {"segment_id": "3zKTB5UC", "annotation_groups": {"segment_boundary": {"group_id": "0", "importance_score": 0, "annotation_type": "segment_boundary", "annotations": [{"annotation_id": "4jVxnlfa", "annotator_id": "ziebermayr", "annotator_type": "human", "annotation_vector": [0.10639336276882444, 0.8668376865671642, 0.34907574396052315, 0.8954446517412935], "is_other": "", "annotation_type": "segment_boundary"}]}, "segment_label": {"group_id": "1", "importance_score": 0, "annotation_type": "segment_label", "annotations": [{"annotation_id": "5Y6n7Z1N", "annotator_id": "ziebermayr", "annotator_type": "human", "annotation_vector": [0, 0, 0, 0, 0, 0, 0, 0, 0, 0], "is_other": "is_other", "annotation_type": "segment_label"}]}, "is_occluded": {"group_id": "2", "importance_score": 0, "annotation_type": "is_occluded", "annotations": [{"annotation_id": "Nu7gUmt2", "annotator_id": "ziebermayr", "annotator_type": "human", "annotation_vector": [0, 1], "is_other": "", "annotation_type": "is_occluded"}]}, "is_truncated": {"group_id": "3", "importance_score": 1, "annotation_type": "is_truncated", "annotations": []}, "segment_type": {"group_id": "4", "importance_score": 0, "annotation_type": "segment_type", "annotations": [{"annotation_id": "0F4vxcW0", "annotator_id": "ziebermayr", "annotator_type": "human", "annotation_vector": [1, 0, 0, 0], "is_other": "", "annotation_type": "segment_type"}]}}, "child_segments": []}, {"segment_id": "Fc6sae9S", "annotation_groups": {"segment_boundary": {"group_id": "0", "importance_score": 0, "annotation_type": "segment_boundary", "annotations": [{"annotation_id": "dCYa6FmQ", "annotator_id": "ziebermayr", "annotator_type": "human", "annotation_vector": [0.2892844326524235, 0.07703669154228855, 0.7060650438294713, 0.18151430348258707], "is_other": "", "annotation_type": "segment_boundary"}]}, "segment_label": {"group_id": "1", "importance_score": 0, "annotation_type": "segment_label", "annotations": [{"annotation_id": "yCy6JiS7", "annotator_id": "ziebermayr", "annotator_type": "human", "annotation_vector": [0, 0, 0, 0, 1, 0, 0, 0, 0, 0], "is_other": "", "annotation_type": "segment_label"}]}, "is_occluded": {"group_id": "2", "importance_score": 0, "annotation_type": "is_occluded", "annotations": [{"annotation_id": "YwApLDZr", "annotator_id": "ziebermayr", "annotator_type": "human", "annotation_vector": [0, 1], "is_other": "", "annotation_type": "is_occluded"}]}, "is_truncated": {"group_id": "3", "importance_score": 1, "annotation_type": "is_truncated", "annotations": []}, "segment_type": {"group_id": "4", "importance_score": 0, "annotation_type": "segment_type", "annotations": [{"annotation_id": "831PLdy8", "annotator_id": "ziebermayr", "annotator_type": "human", "annotation_vector": [0, 1, 0, 0], "is_other": "", "annotation_type": "segment_type"}]}}, "child_segments": []}, {"segment_id": "ohNgRaRZ", "annotation_groups": {"segment_boundary": {"group_id": "0", "importance_score": 0, "annotation_type": "segment_boundary", "annotations": [{"annotation_id": "EHPgEY0Q", "annotator_id": "ziebermayr", "annotator_type": "human", "annotation_vector": [0.09760052287057448, 0.6491759950248757, 0.9170932013874702, 0.759872512437811], "is_other": "", "annotation_type": "segment_boundary"}]}, "segment_label": {"group_id": "1", "importance_score": 0, "annotation_type": "segment_label", "annotations": [{"annotation_id": "SG2H6X9I", "annotator_id": "ziebermayr", "annotator_type": "human", "annotation_vector": [0, 0, 0, 0, 0, 0, 0, 0, 0, 0], "is_other": "Rechnungsinformation", "annotation_type": "segment_label"}]}, "is_occluded": {"group_id": "2", "importance_score": 0, "annotation_type": "is_occluded", "annotations": [{"annotation_id": "pwgU0WIT", "annotator_id": "ziebermayr", "annotator_type": "human", "annotation_vector": [0, 1], "is_other": "", "annotation_type": "is_occluded"}]}, "is_truncated": {"group_id": "3", "importance_score": 1, "annotation_type": "is_truncated", "annotations": []}, "segment_type": {"group_id": "4", "importance_score": 0, "annotation_type": "segment_type", "annotations": [{"annotation_id": "LxoKJ41I", "annotator_id": "ziebermayr", "annotator_type": "human", "annotation_vector": [0, 0, 1, 0], "is_other": "", "annotation_type": "segment_type"}]}}, "child_segments": []}, {"segment_id": "YczFMv1v", "annotation_groups": {"segment_boundary": {"group_id": "0", "importance_score": 0, "annotation_type": "segment_boundary", "annotations": [{"annotation_id": "n91eEc9B", "annotator_id": "ziebermayr", "annotator_type": "human", "annotation_vector": [0.09760052287057448, 0.8618625621890548, 0.3543514478994731, 0.9029073383084577], "is_other": "", "annotation_type": "segment_boundary"}]}, "segment_label": {"group_id": "1", "importance_score": 0, "annotation_type": "segment_label", "annotations": [{"annotation_id": "ml1BSHre", "annotator_id": "ziebermayr", "annotator_type": "human", "annotation_vector": [0, 1, 0, 0, 0, 0, 0, 0, 0, 0], "is_other": "", "annotation_type": "segment_label"}]}, "is_occluded": {"group_id": "2", "importance_score": 0, "annotation_type": "is_occluded", "annotations": [{"annotation_id": "U0DC4jnq", "annotator_id": "ziebermayr", "annotator_type": "human", "annotation_vector": [0, 1], "is_other": "", "annotation_type": "is_occluded"}]}, "is_truncated": {"group_id": "3", "importance_score": 1, "annotation_type": "is_truncated", "annotations": []}, "segment_type": {"group_id": "4", "importance_score": 0, "annotation_type": "segment_type", "annotations": [{"annotation_id": "bEBP8FsL", "annotator_id": "ziebermayr", "annotator_type": "human", "annotation_vector": [1, 0, 0, 0], "is_other": "", "annotation_type": "segment_type"}]}}, "child_segments": []}]}, {"page_number": -1, "segments": [{"segment_id": "x24l78I8", "annotation_groups": {"segment_boundary": {"group_id": "0", "importance_score": 0, "annotation_type": "segment_boundary", "annotations": [{"annotation_id": "mSCJcliJ", "annotator_id": "ziebermayr", "annotator_type": "human", "annotation_vector": [-1, -1, -2, -2], "is_other": "", "annotation_type": "segment_boundary"}]}, "segment_label": {"group_id": "1", "importance_score": 0, "annotation_type": "segment_label", "annotations": [{"annotation_id": "ZAHTXdjB", "annotator_id": "ziebermayr", "annotator_type": "human", "annotation_vector": [0, 0, 1, 0, 0, 0, 0, 0, 0, 0], "is_other": "", "annotation_type": "segment_label"}]}, "is_occluded": {"group_id": "2", "importance_score": 0, "annotation_type": "is_occluded", "annotations": []}, "is_truncated": {"group_id": "3", "importance_score": 0, "annotation_type": "is_truncated", "annotations": []}, "segment_type": {"group_id": "4", "importance_score": 0, "annotation_type": "segment_type", "annotations": []}}, "child_segments": []}, {"segment_id": "ULmO847o", "annotation_groups": {"segment_boundary": {"group_id": "0", "importance_score": 0, "annotation_type": "segment_boundary", "annotations": [{"annotation_id": "7XG3Jb1s", "annotator_id": "ziebermayr", "annotator_type": "human", "annotation_vector": [-1, -1, -2, -2], "is_other": "", "annotation_type": "segment_boundary"}]}, "segment_label": {"group_id": "1", "importance_score": 0, "annotation_type": "segment_label", "annotations": [{"annotation_id": "cvSkfXrJ", "annotator_id": "ziebermayr", "annotator_type": "human", "annotation_vector": [0, 0, 0, 0, 0, 1, 0, 0, 0, 0], "is_other": "", "annotation_type": "segment_label"}]}, "is_occluded": {"group_id": "2", "importance_score": 0, "annotation_type": "is_occluded", "annotations": []}, "is_truncated": {"group_id": "3", "importance_score": 0, "annotation_type": "is_truncated", "annotations": []}, "segment_type": {"group_id": "4", "importance_score": 0, "annotation_type": "segment_type", "annotations": []}}, "child_segments": []}, {"segment_id": "lmTglmd1", "annotation_groups": {"segment_boundary": {"group_id": "0", "importance_score": 0, "annotation_type": "segment_boundary", "annotations": [{"annotation_id": "2wniqStb", "annotator_id": "ziebermayr", "annotator_type": "human", "annotation_vector": [-1, -1, -2, -2], "is_other": "", "annotation_type": "segment_boundary"}]}, "segment_label": {"group_id": "1", "importance_score": 0, "annotation_type": "segment_label", "annotations": [{"annotation_id": "AgDu8Uaa", "annotator_id": "ziebermayr", "annotator_type": "human", "annotation_vector": [0, 0, 0, 0, 0, 0, 1, 0, 0, 0], "is_other": "", "annotation_type": "segment_label"}]}, "is_occluded": {"group_id": "2", "importance_score": 0, "annotation_type": "is_occluded", "annotations": []}, "is_truncated": {"group_id": "3", "importance_score": 0, "annotation_type": "is_truncated", "annotations": []}, "segment_type": {"group_id": "4", "importance_score": 0, "annotation_type": "segment_type", "annotations": []}}, "child_segments": []}, {"segment_id": "YlGVdt05", "annotation_groups": {"segment_boundary": {"group_id": "0", "importance_score": 0, "annotation_type": "segment_boundary", "annotations": [{"annotation_id": "Zl3ZZtfW", "annotator_id": "ziebermayr", "annotator_type": "human", "annotation_vector": [-1, -1, -2, -2], "is_other": "", "annotation_type": "segment_boundary"}]}, "segment_label": {"group_id": "1", "importance_score": 0, "annotation_type": "segment_label", "annotations": [{"annotation_id": "eIj4AtoU", "annotator_id": "ziebermayr", "annotator_type": "human", "annotation_vector": [0, 0, 0, 0, 0, 0, 0, 1, 0, 0], "is_other": "", "annotation_type": "segment_label"}]}, "is_occluded": {"group_id": "2", "importance_score": 0, "annotation_type": "is_occluded", "annotations": []}, "is_truncated": {"group_id": "3", "importance_score": 0, "annotation_type": "is_truncated", "annotations": []}, "segment_type": {"group_id": "4", "importance_score": 0, "annotation_type": "segment_type", "annotations": []}}, "child_segments": []}, {"segment_id": "fA4iweMg", "annotation_groups": {"segment_boundary": {"group_id": "0", "importance_score": 0, "annotation_type": "segment_boundary", "annotations": [{"annotation_id": "XZ5fo0LF", "annotator_id": "ziebermayr", "annotator_type": "human", "annotation_vector": [-1, -1, -2, -2], "is_other": "", "annotation_type": "segment_boundary"}]}, "segment_label": {"group_id": "1", "importance_score": 0, "annotation_type": "segment_label", "annotations": [{"annotation_id": "GH4ao4Qe", "annotator_id": "ziebermayr", "annotator_type": "human", "annotation_vector": [0, 0, 0, 0, 0, 0, 0, 0, 1, 0], "is_other": "", "annotation_type": "segment_label"}]}, "is_occluded": {"group_id": "2", "importance_score": 0, "annotation_type": "is_occluded", "annotations": []}, "is_truncated": {"group_id": "3", "importance_score": 0, "annotation_type": "is_truncated", "annotations": []}, "segment_type": {"group_id": "4", "importance_score": 0, "annotation_type": "segment_type", "annotations": []}}, "child_segments": []}, {"segment_id": "iEvdUf0k", "annotation_groups": {"segment_boundary": {"group_id": "0", "importance_score": 0, "annotation_type": "segment_boundary", "annotations": [{"annotation_id": "xVJuZgWd", "annotator_id": "ziebermayr", "annotator_type": "human", "annotation_vector": [-1, -1, -2, -2], "is_other": "", "annotation_type": "segment_boundary"}]}, "segment_label": {"group_id": "1", "importance_score": 0, "annotation_type": "segment_label", "annotations": []}, "is_occluded": {"group_id": "2", "importance_score": 0, "annotation_type": "is_occluded", "annotations": []}, "is_truncated": {"group_id": "3", "importance_score": 0, "annotation_type": "is_truncated", "annotations": []}, "segment_type": {"group_id": "4", "importance_score": 0, "annotation_type": "segment_type", "annotations": [{"annotation_id": "MHrUZne1", "annotator_id": "ziebermayr", "annotator_type": "human", "annotation_vector": [0, 0, 0, 1], "is_other": "", "annotation_type": "segment_type"}]}}, "child_segments": []}]}], "annotated_by": {"document_contains": [{"name": "Flossi", "timestamp": "2020-04-21T12:00:00.000Z"}], "document_label": [{"name": "Flossi", "timestamp": "2020-04-21T12:00:00.000Z"}], "document_type": [{"name": "Flossi", "timestamp": "2020-04-21T12:00:00.000Z"}], "is_occluded": [{"name": "Dominik", "timestamp": "2020-04-21T12:00:00.000Z"}, {"name": "ziebermayr", "timestamp": "2020-06-03T08:17:40.895Z"}], "is_truncated": [], "segment_boundary": [{"name": "Dominik", "timestamp": "2020-04-21T12:00:00.000Z"}, {"name": "ziebermayr", "timestamp": "2020-06-03T08:10:14.954Z"}], "segment_label": [{"name": "Dominik", "timestamp": "2020-04-21T12:00:00.000Z"}, {"name": "Dominik", "timestamp": "2020-04-21T12:00:00.000Z"}, {"name": "ziebermayr", "timestamp": "2020-06-03T08:10:14.954Z"}, {"name": "ziebermayr", "timestamp": "2020-06-03T08:17:40.895Z"}], "segment_type": [{"name": "Dominik", "timestamp": "2020-04-21T12:00:00.000Z"}, {"name": "Dominik", "timestamp": "2020-04-21T12:00:00.000Z"}, {"name": "ziebermayr", "timestamp": "2020-06-03T08:10:14.954Z"}, {"name": "ziebermayr", "timestamp": "2020-06-03T08:17:40.895Z"}]}, "annotation_completion": "complete", "target_collection": "total_annotation"}