{"document_id": "96b5e71a80f53b71946e5bcf9634a777", "importance_score": 3.1039999999999996, "initial_importance": 1, "origin": "SynthetischerFall", "document_label": {"group_id": "0", "importance_score": 0, "annotation_type": "document_label", "annotations": [{"annotation_id": "0", "annotator_id": "folder_model", "annotator_type": "model", "annotation_vector": [1, 0, 0, 0, 0, 0, 0, 0, 0, 0, 0, 0, 0, 0, 0, 0, 0, 0, 0], "is_other": "", "annotation_type": "document_label"}, {"annotation_id": "3YfpWzjV", "annotator_id": "Ipsi", "annotator_type": "human", "annotation_vector": [1, 0, 0, 0, 0, 0, 0, 0, 0, 0, 0, 0, 0, 0, 0, 0, 0, 0, 0], "is_other": "", "annotation_type": "document_label"}]}, "document_type": {"group_id": "1", "importance_score": 0, "annotation_type": "document_type", "annotations": [{"annotation_id": "wk4wEnJ5", "annotator_id": "Ipsi", "annotator_type": "human", "annotation_vector": [1, 0, 0], "is_other": "", "annotation_type": "document_type"}]}, "document_contains": {"group_id": "2", "importance_score": 0, "annotation_type": "document_contains", "annotations": [{"annotation_id": "VmyRCDrr", "annotator_id": "Ipsi", "annotator_type": "human", "annotation_vector": [1, 1, 0, 1, 1, 1, 0, 0, 0, 1, 1, 1, 1, 0], "is_other": "", "annotation_type": "document_contains"}]}, "pages": [{"page_number": 0, "segments": [{"segment_id": "i1tvR2Dh", "annotation_groups": {"segment_boundary": {"group_id": "0", "importance_score": 0, "annotation_type": "segment_boundary", "annotations": [{"annotation_id": "E4Vw8GDE", "annotator_id": "Dominik", "annotator_type": "human", "annotation_vector": [0.1080809498457669, 0.19951662011741106, 0.4157163122622583, 0.27353328945959476], "is_other": "", "annotation_type": "segment_boundary"}]}, "segment_label": {"group_id": "1", "importance_score": 0, "annotation_type": "segment_label", "annotations": [{"annotation_id": "ibzkSHLF", "annotator_id": "Dominik", "annotator_type": "human", "annotation_vector": [1, 0, 0, 0, 0, 0, 0, 0, 0, 0], "is_other": "", "annotation_type": "segment_label"}]}, "is_occluded": {"group_id": "2", "importance_score": 0, "annotation_type": "is_occluded", "annotations": [{"annotation_id": "mrezjj3t", "annotator_id": "Dominik", "annotator_type": "human", "annotation_vector": [0, 1], "is_other": "", "annotation_type": "is_occluded"}]}, "is_truncated": {"group_id": "3", "importance_score": 1, "annotation_type": "is_truncated", "annotations": []}, "segment_type": {"group_id": "4", "importance_score": 0, "annotation_type": "segment_type", "annotations": [{"annotation_id": "d0q3Tuo3", "annotator_id": "Dominik", "annotator_type": "human", "annotation_vector": [1, 0, 0, 0], "is_other": "", "annotation_type": "segment_type"}]}}, "child_segments": []}, {"segment_id": "5BIdi2to", "annotation_groups": {"segment_boundary": {"group_id": "0", "importance_score": 0, "annotation_type": "segment_boundary", "annotations": [{"annotation_id": "VKtlvJc7", "annotator_id": "Dominik", "annotator_type": "human", "annotation_vector": [0.11235366321266257, 0.8581139228356168, 0.9006692794049219, 0.9200462379994847], "is_other": "", "annotation_type": "segment_boundary"}]}, "segment_label": {"group_id": "1", "importance_score": 0, "annotation_type": "segment_label", "annotations": [{"annotation_id": "S6zGhCZv", "annotator_id": "Dominik", "annotator_type": "human", "annotation_vector": [0, 0, 0, 1, 0, 0, 0, 0, 0, 0], "is_other": "", "annotation_type": "segment_label"}]}, "is_occluded": {"group_id": "2", "importance_score": 0, "annotation_type": "is_occluded", "annotations": [{"annotation_id": "LtGM8Wer", "annotator_id": "Dominik", "annotator_type": "human", "annotation_vector": [0, 1], "is_other": "", "annotation_type": "is_occluded"}]}, "is_truncated": {"group_id": "3", "importance_score": 1, "annotation_type": "is_truncated", "annotations": []}, "segment_type": {"group_id": "4", "importance_score": 0, "annotation_type": "segment_type", "annotations": [{"annotation_id": "JxFkpanX", "annotator_id": "Dominik", "annotator_type": "human", "annotation_vector": [1, 0, 0, 0], "is_other": "", "annotation_type": "segment_type"}]}}, "child_segments": []}, {"segment_id": "VehxxNjU", "annotation_groups": {"segment_boundary": {"group_id": "0", "importance_score": 0, "annotation_type": "segment_boundary", "annotations": [{"annotation_id": "lOXULvbt", "annotator_id": "Dominik", "annotator_type": "human", "annotation_vector": [0.32598933155744836, 0.03486729443785965, 0.5417613565856818, 0.09226797678485921], "is_other": "", "annotation_type": "segment_boundary"}]}, "segment_label": {"group_id": "1", "importance_score": 0, "annotation_type": "segment_label", "annotations": [{"annotation_id": "Xf1nKlcM", "annotator_id": "Dominik", "annotator_type": "human", "annotation_vector": [0, 0, 0, 0, 1, 0, 0, 0, 0, 0], "is_other": "", "annotation_type": "segment_label"}]}, "is_occluded": {"group_id": "2", "importance_score": 0, "annotation_type": "is_occluded", "annotations": [{"annotation_id": "jHs0UFqS", "annotator_id": "Dominik", "annotator_type": "human", "annotation_vector": [0, 1], "is_other": "", "annotation_type": "is_occluded"}]}, "is_truncated": {"group_id": "3", "importance_score": 1, "annotation_type": "is_truncated", "annotations": []}, "segment_type": {"group_id": "4", "importance_score": 0, "annotation_type": "segment_type", "annotations": [{"annotation_id": "mzTnqIKt", "annotator_id": "Dominik", "annotator_type": "human", "annotation_vector": [0, 1, 0, 0], "is_other": "", "annotation_type": "segment_type"}]}}, "child_segments": []}, {"segment_id": "LScarYZe", "annotation_groups": {"segment_boundary": {"group_id": "0", "importance_score": 0, "annotation_type": "segment_boundary", "annotations": [{"annotation_id": "EAj9gTrq", "annotator_id": "Dominik", "annotator_type": "human", "annotation_vector": [0.28326219788849116, 0.006166953264359862, 0.5738067068373998, 0.17383736748849024], "is_other": "", "annotation_type": "segment_boundary"}]}, "segment_label": {"group_id": "1", "importance_score": 0, "annotation_type": "segment_label", "annotations": [{"annotation_id": "hIrcIcsq", "annotator_id": "Dominik", "annotator_type": "human", "annotation_vector": [0, 0, 0, 0, 0, 1, 0, 0, 0, 0], "is_other": "", "annotation_type": "segment_label"}]}, "is_occluded": {"group_id": "2", "importance_score": 0, "annotation_type": "is_occluded", "annotations": [{"annotation_id": "esBMXEwS", "annotator_id": "Dominik", "annotator_type": "human", "annotation_vector": [1, 0], "is_other": "", "annotation_type": "is_occluded"}]}, "is_truncated": {"group_id": "3", "importance_score": 1, "annotation_type": "is_truncated", "annotations": []}, "segment_type": {"group_id": "4", "importance_score": 0, "annotation_type": "segment_type", "annotations": [{"annotation_id": "G1BKWB3C", "annotator_id": "Dominik", "annotator_type": "human", "annotation_vector": [0, 1, 0, 0], "is_other": "", "annotation_type": "segment_type"}]}}, "child_segments": []}, {"segment_id": "ZRb3RTtn", "annotation_groups": {"segment_boundary": {"group_id": "0", "importance_score": 0, "annotation_type": "segment_boundary", "annotations": [{"annotation_id": "903E0dGU", "annotator_id": "Dominik", "annotator_type": "human", "annotation_vector": [0.5438977132691297, 0.08622579969570139, 0.8942602093545783, 0.15117920340414828], "is_other": "", "annotation_type": "segment_boundary"}]}, "segment_label": {"group_id": "1", "importance_score": 0, "annotation_type": "segment_label", "annotations": [{"annotation_id": "cbhY3eKf", "annotator_id": "Dominik", "annotator_type": "human", "annotation_vector": [0, 0, 0, 0, 0, 0, 0, 0, 0, 1], "is_other": "", "annotation_type": "segment_label"}]}, "is_occluded": {"group_id": "2", "importance_score": 0, "annotation_type": "is_occluded", "annotations": [{"annotation_id": "YgRpCqpk", "annotator_id": "Dominik", "annotator_type": "human", "annotation_vector": [1, 0], "is_other": "", "annotation_type": "is_occluded"}]}, "is_truncated": {"group_id": "3", "importance_score": 1, "annotation_type": "is_truncated", "annotations": []}, "segment_type": {"group_id": "4", "importance_score": 0, "annotation_type": "segment_type", "annotations": [{"annotation_id": "aYD9d5zJ", "annotator_id": "Dominik", "annotator_type": "human", "annotation_vector": [1, 0, 0, 0], "is_other": "", "annotation_type": "segment_type"}]}}, "child_segments": []}, {"segment_id": "5XGo5UWL", "annotation_groups": {"segment_boundary": {"group_id": "0", "importance_score": 0, "annotation_type": "segment_boundary", "annotations": [{"annotation_id": "mvmfivNL", "annotator_id": "Dominik", "annotator_type": "human", "annotation_vector": [0.11235366321266257, 0.22066423992946357, 0.41785266894570616, 0.2720227451873053], "is_other": "", "annotation_type": "segment_boundary"}]}, "segment_label": {"group_id": "1", "importance_score": 0, "annotation_type": "segment_label", "annotations": [{"annotation_id": "UKckxpkd", "annotator_id": "Dominik", "annotator_type": "human", "annotation_vector": [0, 0, 0, 0, 0, 0, 0, 0, 0, 1], "is_other": "", "annotation_type": "segment_label"}]}, "is_occluded": {"group_id": "2", "importance_score": 0, "annotation_type": "is_occluded", "annotations": [{"annotation_id": "Y5NrIp4J", "annotator_id": "Dominik", "annotator_type": "human", "annotation_vector": [0, 1], "is_other": "", "annotation_type": "is_occluded"}]}, "is_truncated": {"group_id": "3", "importance_score": 1, "annotation_type": "is_truncated", "annotations": []}, "segment_type": {"group_id": "4", "importance_score": 0, "annotation_type": "segment_type", "annotations": [{"annotation_id": "ntDvQdhe", "annotator_id": "Dominik", "annotator_type": "human", "annotation_vector": [1, 0, 0, 0], "is_other": "", "annotation_type": "segment_type"}]}}, "child_segments": []}, {"segment_id": "zsjOgNTR", "annotation_groups": {"segment_boundary": {"group_id": "0", "importance_score": 0, "annotation_type": "segment_boundary", "annotations": [{"annotation_id": "f1qBeQSm", "annotator_id": "Dominik", "annotator_type": "human", "annotation_vector": [0.6186701971898048, 0.26295947955356846, 0.8258967954842471, 0.3128074405391208], "is_other": "", "annotation_type": "segment_boundary"}]}, "segment_label": {"group_id": "1", "importance_score": 0, "annotation_type": "segment_label", "annotations": [{"annotation_id": "6nLQtbkz", "annotator_id": "Dominik", "annotator_type": "human", "annotation_vector": [0, 0, 0, 0, 0, 0, 0, 0, 0, 1], "is_other": "", "annotation_type": "segment_label"}]}, "is_occluded": {"group_id": "2", "importance_score": 0, "annotation_type": "is_occluded", "annotations": [{"annotation_id": "0DZbPeYj", "annotator_id": "Dominik", "annotator_type": "human", "annotation_vector": [0, 1], "is_other": "", "annotation_type": "is_occluded"}]}, "is_truncated": {"group_id": "3", "importance_score": 1, "annotation_type": "is_truncated", "annotations": []}, "segment_type": {"group_id": "4", "importance_score": 0, "annotation_type": "segment_type", "annotations": [{"annotation_id": "Avdnxcl8", "annotator_id": "Dominik", "annotator_type": "human", "annotation_vector": [1, 0, 0, 0], "is_other": "", "annotation_type": "segment_type"}]}}, "child_segments": []}, {"segment_id": "Y6cWbuuI", "annotation_groups": {"segment_boundary": {"group_id": "0", "importance_score": 0, "annotation_type": "segment_boundary", "annotations": [{"annotation_id": "7bgMY8HA", "annotator_id": "Dominik", "annotator_type": "human", "annotation_vector": [0.10594459316231901, 0.8626455556524852, 0.9070783494552654, 0.8853037197368271], "is_other": "", "annotation_type": "segment_boundary"}]}, "segment_label": {"group_id": "1", "importance_score": 0, "annotation_type": "segment_label", "annotations": [{"annotation_id": "cc1mG7ID", "annotator_id": "Dominik", "annotator_type": "human", "annotation_vector": [0, 0, 0, 0, 0, 0, 0, 0, 0, 1], "is_other": "", "annotation_type": "segment_label"}]}, "is_occluded": {"group_id": "2", "importance_score": 0, "annotation_type": "is_occluded", "annotations": [{"annotation_id": "xm2cRuWM", "annotator_id": "Dominik", "annotator_type": "human", "annotation_vector": [0, 1], "is_other": "", "annotation_type": "is_occluded"}]}, "is_truncated": {"group_id": "3", "importance_score": 1, "annotation_type": "is_truncated", "annotations": []}, "segment_type": {"group_id": "4", "importance_score": 0, "annotation_type": "segment_type", "annotations": [{"annotation_id": "rVTErE8F", "annotator_id": "Dominik", "annotator_type": "human", "annotation_vector": [1, 0, 0, 0], "is_other": "", "annotation_type": "segment_type"}]}}, "child_segments": []}, {"segment_id": "mCyaGw3w", "annotation_groups": {"segment_boundary": {"group_id": "0", "importance_score": 0, "annotation_type": "segment_boundary", "annotations": [{"annotation_id": "Ew7V8Cw7", "annotator_id": "Dominik", "annotator_type": "human", "annotation_vector": [0.11021730652921471, 0.7327387482355914, 0.9049419927718177, 0.8430084801127222], "is_other": "", "annotation_type": "segment_boundary"}]}, "segment_label": {"group_id": "1", "importance_score": 0, "annotation_type": "segment_label", "annotations": [{"annotation_id": "oN4VyKuS", "annotator_id": "Dominik", "annotator_type": "human", "annotation_vector": [0, 0, 0, 0, 0, 0, 0, 0, 0, 0], "is_other": "Zahlungskonditionen", "annotation_type": "segment_label"}]}, "is_occluded": {"group_id": "2", "importance_score": 0, "annotation_type": "is_occluded", "annotations": [{"annotation_id": "YDOtfNWd", "annotator_id": "Dominik", "annotator_type": "human", "annotation_vector": [0, 1], "is_other": "", "annotation_type": "is_occluded"}]}, "is_truncated": {"group_id": "3", "importance_score": 1, "annotation_type": "is_truncated", "annotations": []}, "segment_type": {"group_id": "4", "importance_score": 0, "annotation_type": "segment_type", "annotations": [{"annotation_id": "tEdP7Mje", "annotator_id": "Dominik", "annotator_type": "human", "annotation_vector": [1, 0, 0, 0], "is_other": "", "annotation_type": "segment_type"}]}}, "child_segments": []}, {"segment_id": "Z6nFwWBW", "annotation_groups": {"segment_boundary": {"group_id": "0", "importance_score": 0, "annotation_type": "segment_boundary", "annotations": [{"annotation_id": "PUvQHE1o", "annotator_id": "Dominik", "annotator_type": "human", "annotation_vector": [0.2768531278381476, 0.004656408992070399, 0.5652612801036083, 0.17383736748849024], "is_other": "", "annotation_type": "segment_boundary"}]}, "segment_label": {"group_id": "1", "importance_score": 0, "annotation_type": "segment_label", "annotations": [{"annotation_id": "kStcOt5r", "annotator_id": "Dominik", "annotator_type": "human", "annotation_vector": [0, 0, 0, 0, 0, 1, 0, 0, 0, 0], "is_other": "", "annotation_type": "segment_label"}]}, "is_occluded": {"group_id": "2", "importance_score": 0, "annotation_type": "is_occluded", "annotations": [{"annotation_id": "6oxJYcwk", "annotator_id": "Dominik", "annotator_type": "human", "annotation_vector": [1, 0], "is_other": "", "annotation_type": "is_occluded"}]}, "is_truncated": {"group_id": "3", "importance_score": 1, "annotation_type": "is_truncated", "annotations": []}, "segment_type": {"group_id": "4", "importance_score": 0, "annotation_type": "segment_type", "annotations": [{"annotation_id": "qbO7ukYV", "annotator_id": "Dominik", "annotator_type": "human", "annotation_vector": [0, 1, 0, 0], "is_other": "", "annotation_type": "segment_type"}]}}, "child_segments": []}, {"segment_id": "p7LfVPiq", "annotation_groups": {"segment_boundary": {"group_id": "0", "importance_score": 0, "annotation_type": "segment_boundary", "annotations": [{"annotation_id": "QWG3fNRb", "annotator_id": "Dominik", "annotator_type": "human", "annotation_vector": [0.09953552311197542, 0.3324445160788838, 0.9070783494552656, 0.7297176596910124], "is_other": "", "annotation_type": "segment_boundary"}]}, "segment_label": {"group_id": "1", "importance_score": 0, "annotation_type": "segment_label", "annotations": [{"annotation_id": "CtaGDtkF", "annotator_id": "Dominik", "annotator_type": "human", "annotation_vector": [0, 0, 0, 0, 0, 0, 0, 0, 0, 0], "is_other": "Kalkulation", "annotation_type": "segment_label"}]}, "is_occluded": {"group_id": "2", "importance_score": 0, "annotation_type": "is_occluded", "annotations": [{"annotation_id": "nZliZ0Am", "annotator_id": "Dominik", "annotator_type": "human", "annotation_vector": [0, 1], "is_other": "", "annotation_type": "is_occluded"}]}, "is_truncated": {"group_id": "3", "importance_score": 1, "annotation_type": "is_truncated", "annotations": []}, "segment_type": {"group_id": "4", "importance_score": 0, "annotation_type": "segment_type", "annotations": [{"annotation_id": "o4rsWn08", "annotator_id": "Dominik", "annotator_type": "human", "annotation_vector": [0, 0, 1, 0], "is_other": "", "annotation_type": "segment_type"}]}}, "child_segments": []}]}, {"page_number": -1, "segments": [{"segment_id": "wl9iMcP9", "annotation_groups": {"segment_boundary": {"group_id": "0", "importance_score": 0, "annotation_type": "segment_boundary", "annotations": [{"annotation_id": "AkGiTHqd", "annotator_id": "Dominik", "annotator_type": "human", "annotation_vector": [-1, -1, -2, -2], "is_other": "", "annotation_type": "segment_boundary"}]}, "segment_label": {"group_id": "1", "importance_score": 0, "annotation_type": "segment_label", "annotations": []}, "is_occluded": {"group_id": "2", "importance_score": 0, "annotation_type": "is_occluded", "annotations": []}, "is_truncated": {"group_id": "3", "importance_score": 0, "annotation_type": "is_truncated", "annotations": []}, "segment_type": {"group_id": "4", "importance_score": 0, "annotation_type": "segment_type", "annotations": []}}, "child_segments": []}]}], "annotated_by": {"document_contains": [{"name": "Ipsi", "timestamp": "2020-04-21T12:00:00.000Z"}], "document_label": [{"name": "Ipsi", "timestamp": "2020-04-21T12:00:00.000Z"}], "document_type": [{"name": "Ipsi", "timestamp": "2020-04-21T12:00:00.000Z"}], "is_occluded": [{"name": "Dominik", "timestamp": "2020-04-21T12:00:00.000Z"}], "is_truncated": [], "segment_boundary": [{"name": "Dominik", "timestamp": "2020-04-21T12:00:00.000Z"}], "segment_label": [{"name": "Dominik", "timestamp": "2020-04-21T12:00:00.000Z"}, {"name": "Dominik", "timestamp": "2020-04-21T12:00:00.000Z"}], "segment_type": [{"name": "Dominik", "timestamp": "2020-04-21T12:00:00.000Z"}, {"name": "Dominik", "timestamp": "2020-04-21T12:00:00.000Z"}]}, "annotation_completion": "complete"}