{"document_id": "d0ad3a762b163604ebdb71a5b42a76ea", "importance_score": 1.424, "initial_importance": 1, "origin": "SynthetischerFall", "document_label": {"group_id": "0", "importance_score": 0, "annotation_type": "document_label", "annotations": [{"annotation_id": "0", "annotator_id": "folder_model", "annotator_type": "model", "annotation_vector": [0, 0, 0, 0, 0, 0, 0, 0, 0, 0, 0, 0, 0, 0, 0, 0, 0, 0, 1], "is_other": "", "annotation_type": "document_label"}, {"annotation_id": "bbCLg9Q6", "annotator_id": "Flossi", "annotator_type": "human", "annotation_vector": [0, 0, 0, 0, 0, 0, 0, 0, 0, 0, 0, 0, 0, 0, 0, 0, 0, 0, 1], "is_other": "", "annotation_type": "document_label"}]}, "document_type": {"group_id": "1", "importance_score": 0, "annotation_type": "document_type", "annotations": [{"annotation_id": "EqG5582f", "annotator_id": "Flossi", "annotator_type": "human", "annotation_vector": [0, 0, 0], "is_other": "is_other", "annotation_type": "document_type"}]}, "document_contains": {"group_id": "2", "importance_score": 0, "annotation_type": "document_contains", "annotations": [{"annotation_id": "m5QIt3Aj", "annotator_id": "Flossi", "annotator_type": "human", "annotation_vector": [0, 0, 0, 1, 0, 0, 0, 0, 0, 1, 0, 0, 1, 0], "is_other": "", "annotation_type": "document_contains"}]}, "pages": [{"page_number": 0, "segments": [{"segment_id": "Y60c2I5x", "annotation_groups": {"segment_boundary": {"group_id": "0", "importance_score": 0, "annotation_type": "segment_boundary", "annotations": [{"annotation_id": "VHLUWdbJ", "annotator_id": "Ipsi", "annotator_type": "human", "annotation_vector": [0.10089197931184765, 0.9292137873567019, 0.8890279952176897, 0.9596305653886341], "is_other": "", "annotation_type": "segment_boundary"}]}, "segment_label": {"group_id": "1", "importance_score": 0, "annotation_type": "segment_label", "annotations": [{"annotation_id": "0nIfDWQy", "annotator_id": "Ipsi", "annotator_type": "human", "annotation_vector": [0, 0, 0, 1, 0, 0, 0, 0, 0, 0], "is_other": "", "annotation_type": "segment_label"}]}, "is_occluded": {"group_id": "2", "importance_score": 0, "annotation_type": "is_occluded", "annotations": [{"annotation_id": "d0ALd1Kj", "annotator_id": "Ipsi", "annotator_type": "human", "annotation_vector": [0, 1], "is_other": "", "annotation_type": "is_occluded"}]}, "is_truncated": {"group_id": "3", "importance_score": 1, "annotation_type": "is_truncated", "annotations": []}, "segment_type": {"group_id": "4", "importance_score": 0, "annotation_type": "segment_type", "annotations": [{"annotation_id": "htRE6fl0", "annotator_id": "Ipsi", "annotator_type": "human", "annotation_vector": [1, 0, 0, 0], "is_other": "", "annotation_type": "segment_type"}]}}, "child_segments": []}, {"segment_id": "25tKzyG2", "annotation_groups": {"segment_boundary": {"group_id": "0", "importance_score": 0, "annotation_type": "segment_boundary", "annotations": [{"annotation_id": "69Wjs4Mv", "annotator_id": "Ipsi", "annotator_type": "human", "annotation_vector": [0.10407636725490155, 0.1980845672558148, 0.4893873083644243, 0.24652610264000302], "is_other": "", "annotation_type": "segment_boundary"}]}, "segment_label": {"group_id": "1", "importance_score": 0, "annotation_type": "segment_label", "annotations": [{"annotation_id": "ZNyJTqwD", "annotator_id": "Ipsi", "annotator_type": "human", "annotation_vector": [0, 0, 0, 0, 0, 0, 0, 0, 0, 1], "is_other": "", "annotation_type": "segment_label"}]}, "is_occluded": {"group_id": "2", "importance_score": 0, "annotation_type": "is_occluded", "annotations": [{"annotation_id": "zNs180iS", "annotator_id": "Ipsi", "annotator_type": "human", "annotation_vector": [0, 1], "is_other": "", "annotation_type": "is_occluded"}]}, "is_truncated": {"group_id": "3", "importance_score": 1, "annotation_type": "is_truncated", "annotations": []}, "segment_type": {"group_id": "4", "importance_score": 0, "annotation_type": "segment_type", "annotations": [{"annotation_id": "aXDcbWvK", "annotator_id": "Ipsi", "annotator_type": "human", "annotation_vector": [0, 0, 1, 0], "is_other": "", "annotation_type": "segment_type"}]}}, "child_segments": []}, {"segment_id": "W0ZKM4Xh", "annotation_groups": {"segment_boundary": {"group_id": "0", "importance_score": 0, "annotation_type": "segment_boundary", "annotations": [{"annotation_id": "TjcjMqNs", "annotator_id": "Ipsi", "annotator_type": "human", "annotation_vector": [0.10566856122642851, 0.27018359666483915, 0.9017655469899054, 0.8143059592360696], "is_other": "", "annotation_type": "segment_boundary"}]}, "segment_label": {"group_id": "1", "importance_score": 0, "annotation_type": "segment_label", "annotations": [{"annotation_id": "3ZZxghOs", "annotator_id": "Ipsi", "annotator_type": "human", "annotation_vector": [0, 0, 0, 0, 0, 0, 0, 0, 0, 0], "is_other": "Saldenliste", "annotation_type": "segment_label"}]}, "is_occluded": {"group_id": "2", "importance_score": 0, "annotation_type": "is_occluded", "annotations": [{"annotation_id": "mmCHkXiB", "annotator_id": "Ipsi", "annotator_type": "human", "annotation_vector": [0, 1], "is_other": "", "annotation_type": "is_occluded"}]}, "is_truncated": {"group_id": "3", "importance_score": 1, "annotation_type": "is_truncated", "annotations": []}, "segment_type": {"group_id": "4", "importance_score": 0, "annotation_type": "segment_type", "annotations": [{"annotation_id": "UDVL2dT6", "annotator_id": "Ipsi", "annotator_type": "human", "annotation_vector": [0, 0, 1, 0], "is_other": "", "annotation_type": "segment_type"}]}}, "child_segments": []}]}], "annotated_by": {"document_contains": [{"name": "Flossi", "timestamp": "2020-04-21T12:00:00.000Z"}], "document_label": [{"name": "Flossi", "timestamp": "2020-04-21T12:00:00.000Z"}], "document_type": [{"name": "Flossi", "timestamp": "2020-04-21T12:00:00.000Z"}], "is_occluded": [{"name": "Ipsi", "timestamp": "2020-04-21T12:00:00.000Z"}], "is_truncated": [], "segment_boundary": [{"name": "Ipsi", "timestamp": "2020-04-21T12:00:00.000Z"}], "segment_label": [{"name": "Ipsi", "timestamp": "2020-04-21T12:00:00.000Z"}, {"name": "Ipsi", "timestamp": "2020-04-21T12:00:00.000Z"}], "segment_type": [{"name": "Ipsi", "timestamp": "2020-04-21T12:00:00.000Z"}, {"name": "Ipsi", "timestamp": "2020-04-21T12:00:00.000Z"}]}, "annotation_completion": "complete"}