{"document_id": "eb07142b48fe66b2a28a3152c526d4c6", "importance_score": 2.7199999999999998, "initial_importance": 1, "origin": "Musterdokumente", "document_label": {"group_id": "0", "importance_score": 0, "annotation_type": "document_label", "annotations": [{"annotation_id": "0", "annotator_id": "folder_model", "annotator_type": "model", "annotation_vector": [0, 0, 0, 0, 0, 0, 0, 0, 0, 0, 0, 0, 0, 0, 0, 0, 0, 0, 0], "is_other": "unknown", "annotation_type": "document_label"}, {"annotation_id": "do5FQJ4O", "annotator_id": "schne", "annotator_type": "human", "annotation_vector": [0, 0, 0, 0, 0, 0, 0, 0, 0, 0, 0, 0, 0, 0, 0, 0, 0, 0, 0], "is_other": "is_other", "annotation_type": "document_label"}]}, "document_type": {"group_id": "1", "importance_score": 0, "annotation_type": "document_type", "annotations": [{"annotation_id": "Ms4FPSXJ", "annotator_id": "schne", "annotator_type": "human", "annotation_vector": [1, 0, 0], "is_other": "", "annotation_type": "document_type"}]}, "document_contains": {"group_id": "2", "importance_score": 0, "annotation_type": "document_contains", "annotations": [{"annotation_id": "h4tPJUCt", "annotator_id": "schne", "annotator_type": "human", "annotation_vector": [1, 1, 1, 1, 1, 0, 0, 0, 0, 0, 1, 1, 0, 0], "is_other": "", "annotation_type": "document_contains"}]}, "pages": [{"page_number": 0, "segments": [{"segment_id": "BmO57yPC", "annotation_groups": {"segment_boundary": {"group_id": "0", "importance_score": 0, "annotation_type": "segment_boundary", "annotations": [{"annotation_id": "xSUYN2HC", "annotator_id": "Ipsi", "annotator_type": "human", "annotation_vector": [0.09773329256669286, 0.15303431359548147, 0.29362466516785746, 0.21837902908675755], "is_other": "", "annotation_type": "segment_boundary"}]}, "segment_label": {"group_id": "1", "importance_score": 0, "annotation_type": "segment_label", "annotations": [{"annotation_id": "eezqP3qQ", "annotator_id": "Ipsi", "annotator_type": "human", "annotation_vector": [1, 0, 0, 0, 0, 0, 0, 0, 0, 0], "is_other": "", "annotation_type": "segment_label"}]}, "is_occluded": {"group_id": "2", "importance_score": 0, "annotation_type": "is_occluded", "annotations": [{"annotation_id": "MQU58Dy1", "annotator_id": "Ipsi", "annotator_type": "human", "annotation_vector": [0, 1], "is_other": "", "annotation_type": "is_occluded"}]}, "is_truncated": {"group_id": "3", "importance_score": 1, "annotation_type": "is_truncated", "annotations": []}, "segment_type": {"group_id": "4", "importance_score": 0, "annotation_type": "segment_type", "annotations": [{"annotation_id": "z1wDwafM", "annotator_id": "Ipsi", "annotator_type": "human", "annotation_vector": [1, 0, 0, 0], "is_other": "", "annotation_type": "segment_type"}]}}, "child_segments": []}, {"segment_id": "3t0WrwGu", "annotation_groups": {"segment_boundary": {"group_id": "0", "importance_score": 0, "annotation_type": "segment_boundary", "annotations": [{"annotation_id": "FCMFXDP5", "annotator_id": "Ipsi", "annotator_type": "human", "annotation_vector": [0.10251113092281884, 0.562002101928813, 0.4719972971298936, 0.6712855054228436], "is_other": "", "annotation_type": "segment_boundary"}]}, "segment_label": {"group_id": "1", "importance_score": 0, "annotation_type": "segment_label", "annotations": [{"annotation_id": "wocSBiZ6", "annotator_id": "Ipsi", "annotator_type": "human", "annotation_vector": [0, 1, 0, 0, 0, 0, 0, 0, 0, 0], "is_other": "", "annotation_type": "segment_label"}]}, "is_occluded": {"group_id": "2", "importance_score": 0, "annotation_type": "is_occluded", "annotations": [{"annotation_id": "Hot9fPgC", "annotator_id": "Ipsi", "annotator_type": "human", "annotation_vector": [0, 1], "is_other": "", "annotation_type": "is_occluded"}]}, "is_truncated": {"group_id": "3", "importance_score": 1, "annotation_type": "is_truncated", "annotations": []}, "segment_type": {"group_id": "4", "importance_score": 0, "annotation_type": "segment_type", "annotations": [{"annotation_id": "A1LwS7Uu", "annotator_id": "Ipsi", "annotator_type": "human", "annotation_vector": [1, 0, 0, 0], "is_other": "", "annotation_type": "segment_type"}]}}, "child_segments": []}, {"segment_id": "MJHQOuS1", "annotation_groups": {"segment_boundary": {"group_id": "0", "importance_score": 0, "annotation_type": "segment_boundary", "annotations": [{"annotation_id": "MMk96bsJ", "annotator_id": "Ipsi", "annotator_type": "human", "annotation_vector": [0.07862193914218898, 0.05163734128143237, 0.894039685254354, 0.1496544145183465], "is_other": "", "annotation_type": "segment_boundary"}]}, "segment_label": {"group_id": "1", "importance_score": 0, "annotation_type": "segment_label", "annotations": [{"annotation_id": "8qj3NQeC", "annotator_id": "Ipsi", "annotator_type": "human", "annotation_vector": [0, 0, 1, 0, 0, 0, 0, 0, 0, 0], "is_other": "", "annotation_type": "segment_label"}]}, "is_occluded": {"group_id": "2", "importance_score": 0, "annotation_type": "is_occluded", "annotations": [{"annotation_id": "nGj6yoK4", "annotator_id": "Ipsi", "annotator_type": "human", "annotation_vector": [0, 1], "is_other": "", "annotation_type": "is_occluded"}]}, "is_truncated": {"group_id": "3", "importance_score": 1, "annotation_type": "is_truncated", "annotations": []}, "segment_type": {"group_id": "4", "importance_score": 0, "annotation_type": "segment_type", "annotations": [{"annotation_id": "tVL2nP1m", "annotator_id": "Ipsi", "annotator_type": "human", "annotation_vector": [1, 0, 0, 0], "is_other": "", "annotation_type": "segment_type"}]}}, "child_segments": []}, {"segment_id": "HnThxffn", "annotation_groups": {"segment_boundary": {"group_id": "0", "importance_score": 0, "annotation_type": "segment_boundary", "annotations": [{"annotation_id": "EQbEQbrJ", "annotator_id": "Ipsi", "annotator_type": "human", "annotation_vector": [0.12162248434732269, 0.9284582747698708, 0.9290771665326112, 0.9847899260554535], "is_other": "", "annotation_type": "segment_boundary"}]}, "segment_label": {"group_id": "1", "importance_score": 0, "annotation_type": "segment_label", "annotations": [{"annotation_id": "nbcDH8og", "annotator_id": "Ipsi", "annotator_type": "human", "annotation_vector": [0, 0, 0, 1, 0, 0, 0, 0, 0, 0], "is_other": "", "annotation_type": "segment_label"}]}, "is_occluded": {"group_id": "2", "importance_score": 0, "annotation_type": "is_occluded", "annotations": [{"annotation_id": "fiD8zjTM", "annotator_id": "Ipsi", "annotator_type": "human", "annotation_vector": [0, 1], "is_other": "", "annotation_type": "is_occluded"}]}, "is_truncated": {"group_id": "3", "importance_score": 1, "annotation_type": "is_truncated", "annotations": []}, "segment_type": {"group_id": "4", "importance_score": 0, "annotation_type": "segment_type", "annotations": [{"annotation_id": "cFFSdfuI", "annotator_id": "Ipsi", "annotator_type": "human", "annotation_vector": [1, 0, 0, 0], "is_other": "", "annotation_type": "segment_type"}]}}, "child_segments": []}, {"segment_id": "6Zee7DjW", "annotation_groups": {"segment_boundary": {"group_id": "0", "importance_score": 0, "annotation_type": "segment_boundary", "annotations": [{"annotation_id": "hLcnGSgH", "annotator_id": "Ipsi", "annotator_type": "human", "annotation_vector": [0.1009185181374435, 0.04855788168906683, 0.31910646973386264, 0.10038300087180303], "is_other": "", "annotation_type": "segment_boundary"}]}, "segment_label": {"group_id": "1", "importance_score": 0, "annotation_type": "segment_label", "annotations": [{"annotation_id": "aobGOdEI", "annotator_id": "Ipsi", "annotator_type": "human", "annotation_vector": [0, 0, 0, 0, 1, 0, 0, 0, 0, 0], "is_other": "", "annotation_type": "segment_label"}]}, "is_occluded": {"group_id": "2", "importance_score": 0, "annotation_type": "is_occluded", "annotations": [{"annotation_id": "7qODnVwc", "annotator_id": "Ipsi", "annotator_type": "human", "annotation_vector": [0, 1], "is_other": "", "annotation_type": "is_occluded"}]}, "is_truncated": {"group_id": "3", "importance_score": 1, "annotation_type": "is_truncated", "annotations": []}, "segment_type": {"group_id": "4", "importance_score": 0, "annotation_type": "segment_type", "annotations": [{"annotation_id": "J5h2Lq6Q", "annotator_id": "Ipsi", "annotator_type": "human", "annotation_vector": [1, 0, 0, 0], "is_other": "", "annotation_type": "segment_type"}]}}, "child_segments": []}, {"segment_id": "qIsdMu3X", "annotation_groups": {"segment_boundary": {"group_id": "0", "importance_score": 0, "annotation_type": "segment_boundary", "annotations": [{"annotation_id": "GJp69UVa", "annotator_id": "Ipsi", "annotator_type": "human", "annotation_vector": [0.11047419484969544, 0.37415482611973566, 0.9593368094547422, 0.5623025414135823], "is_other": "", "annotation_type": "segment_boundary"}]}, "segment_label": {"group_id": "1", "importance_score": 0, "annotation_type": "segment_label", "annotations": [{"annotation_id": "S4iwtyW4", "annotator_id": "Ipsi", "annotator_type": "human", "annotation_vector": [0, 0, 0, 0, 0, 0, 0, 0, 0, 0], "is_other": "is_other", "annotation_type": "segment_label"}]}, "is_occluded": {"group_id": "2", "importance_score": 0, "annotation_type": "is_occluded", "annotations": [{"annotation_id": "D1h8EYoK", "annotator_id": "Ipsi", "annotator_type": "human", "annotation_vector": [0, 1], "is_other": "", "annotation_type": "is_occluded"}]}, "is_truncated": {"group_id": "3", "importance_score": 1, "annotation_type": "is_truncated", "annotations": []}, "segment_type": {"group_id": "4", "importance_score": 0, "annotation_type": "segment_type", "annotations": [{"annotation_id": "QykVS1eY", "annotator_id": "Ipsi", "annotator_type": "human", "annotation_vector": [1, 0, 0, 0], "is_other": "", "annotation_type": "segment_type"}]}}, "child_segments": []}]}, {"page_number": -1, "segments": [{"segment_id": "f2u39rg3", "annotation_groups": {"segment_boundary": {"group_id": "0", "importance_score": 0, "annotation_type": "segment_boundary", "annotations": [{"annotation_id": "qugoc6Lx", "annotator_id": "Ipsi", "annotator_type": "human", "annotation_vector": [-1, -1, -2, -2], "is_other": "", "annotation_type": "segment_boundary"}]}, "segment_label": {"group_id": "1", "importance_score": 0, "annotation_type": "segment_label", "annotations": []}, "is_occluded": {"group_id": "2", "importance_score": 0, "annotation_type": "is_occluded", "annotations": []}, "is_truncated": {"group_id": "3", "importance_score": 0, "annotation_type": "is_truncated", "annotations": []}, "segment_type": {"group_id": "4", "importance_score": 0, "annotation_type": "segment_type", "annotations": []}}, "child_segments": []}]}], "annotated_by": {"document_contains": [{"name": "schne", "timestamp": "2020-04-21T12:00:00.000Z"}], "document_label": [{"name": "schne", "timestamp": "2020-04-21T12:00:00.000Z"}], "document_type": [{"name": "schne", "timestamp": "2020-04-21T12:00:00.000Z"}], "is_occluded": [{"name": "Ipsi", "timestamp": "2020-04-21T12:00:00.000Z"}], "is_truncated": [], "segment_boundary": [{"name": "Ipsi", "timestamp": "2020-04-21T12:00:00.000Z"}], "segment_label": [{"name": "Ipsi", "timestamp": "2020-04-21T12:00:00.000Z"}, {"name": "Ipsi", "timestamp": "2020-04-21T12:00:00.000Z"}], "segment_type": [{"name": "Ipsi", "timestamp": "2020-04-21T12:00:00.000Z"}, {"name": "Ipsi", "timestamp": "2020-04-21T12:00:00.000Z"}]}, "annotation_completion": "complete"}